{"resultCode":"0000","msg":"成功","response":[{"hospitalId":"1121","hospitalName":"中山大学附属第三医院(萝岗)（岭南医院)","departmentId":"204000","departmentName":"血液内科门诊[萝岗]","doctorId":"349126","doctorName":"张祥忠","status":null,"spId":null,"spCode":null,"regSubject":"","verNum":null,"priority":null,"sex":"1","birthday":"","title":"副主任医师","fee":"","intro":"","specialty":"对血液系统各类贫血(缺铁性贫血，巨幼细胞贫血，再生障碍性贫血等)、出血(血小板减少性紫癜，遗传性、获得性凝血因子障碍)和血液恶性肿瘤(急、慢性白血病，淋巴瘤及多发性骨髓瘤等)等疾病的诊治积累了丰富的临床经验。","notice":"","photo":"http://183.63.133.156:8015/dl/photos/doctor/doctor_349126.jpg","hot":"1","level":"","sendSpCode":null,"reviewScore":"4","doctorsAttitude":"4","treatmentEffect":"4","favStatis":"","orderStatis":"","reviewStatis":"","hasResource":true,"schedules":[],"member":"DOCTOR_349126","score":0.0},{"hospitalId":"1121","hospitalName":"中山大学附属第三医院(萝岗)（岭南医院)","departmentId":"204000","departmentName":"血液内科门诊[萝岗]","doctorId":"350633","doctorName":"肖若芝","status":null,"spId":null,"spCode":null,"regSubject":"","verNum":null,"priority":null,"sex":"0","birthday":"","title":"主任医师","fee":"","intro":"","specialty":"擅长诊断和治疗血液系统的常见病、多发病，例如各种贫血、急慢性白血病、骨髓增生异常综合症、恶性淋巴瘤、多发性骨髓瘤、骨髓增殖性疾病和血小板减少性紫癜等。 ","notice":"","photo":"http://183.63.133.156:8015/dl/photos/doctor/doctor_350633.jpg","hot":"1","level":"","sendSpCode":null,"reviewScore":"4","doctorsAttitude":"4","treatmentEffect":"4","favStatis":"","orderStatis":"","reviewStatis":"","hasResource":true,"schedules":[{"departmentCode":"591","departmentName":"血液内科门诊[萝岗]","doctorCode":"1592","doctorName":"肖若芝","scheDate":"2016-07-18","amPm":"下午","state":"1","freeNum":"-1","returnMsg":"12953||176","payType":"0"}],"member":"DOCTOR_350633","score":0.0},{"hospitalId":"1121","hospitalName":"中山大学附属第三医院(萝岗)（岭南医院)","departmentId":"204000","departmentName":"血液内科门诊[萝岗]","doctorId":"383288","doctorName":"血液专科门诊","status":null,"spId":null,"spCode":null,"regSubject":"","verNum":null,"priority":null,"sex":"-1","birthday":"","title":"医师","fee":"","intro":"","specialty":"","notice":"","photo":"","hot":"1","level":"","sendSpCode":null,"reviewScore":"4","doctorsAttitude":"4","treatmentEffect":"4","favStatis":"","orderStatis":"","reviewStatis":"","hasResource":true,"schedules":[{"departmentCode":"591","departmentName":"血液内科门诊[萝岗]","doctorCode":"4794","doctorName":"血液专科门诊","scheDate":"2016-07-20","amPm":"下午","state":"0","freeNum":"78","returnMsg":"9242||340","payType":"0"}],"member":"DOCTOR_383288","score":0.0},{"hospitalId":"1121","hospitalName":"中山大学附属第三医院(萝岗)（岭南医院)","departmentId":"204000","departmentName":"血液内科门诊[萝岗]","doctorId":"670161","doctorName":"林东军","status":null,"spId":null,"spCode":null,"regSubject":"","verNum":null,"priority":null,"sex":"1","birthday":"","title":"主任医师","fee":"","intro":"","specialty":"擅长白血病、淋巴瘤和贫血诊治及造血干细胞移植等血液内科疾病","notice":"","photo":"http://183.63.133.156:8015/dl/photos/doctor/doctor_670161.jpg","hot":"1","level":"","sendSpCode":null,"reviewScore":"4","doctorsAttitude":"4","treatmentEffect":"4","favStatis":"","orderStatis":"","reviewStatis":"","hasResource":true,"schedules":[{"departmentCode":"591","departmentName":"血液内科门诊[萝岗]","doctorCode":"902","doctorName":"林东军","scheDate":"2016-07-22","amPm":"上午","state":"0","freeNum":"14","returnMsg":"15348||60","payType":"0"}],"member":"DOCTOR_670161","score":0.0}],"sum":4,"days":["2016-07-16 星期六","2016-07-17 星期日","2016-07-18 星期一","2016-07-19 星期二","2016-07-20 星期三","2016-07-21 星期四","2016-07-22 星期五","2016-07-23 星期六"],"index":4}