{"resultCode":"0000","msg":"成功","response":[{"hospitalId":"1775","hospitalName":"广东省第二中医院(白云院区)","departmentId":"215929","departmentName":"白云分院专家特需门诊","doctorId":"439342","doctorName":"蔡妙珊","status":null,"spId":null,"spCode":null,"regSubject":"","verNum":null,"priority":null,"sex":"0","birthday":"","title":"主任中医师","fee":"","intro":"广东省名中医 主任中医师 专长：高血压、冠心病、糖尿病、","specialty":"诊治内科常见病、多发病及疑难杂症。尤其擅长肝、胆、脾、肾及妇科疾病的诊治，如溃疡病、糖尿病、急性肝炎、胆囊炎及肾炎等","notice":"","photo":"http://183.63.133.156:8015/dl/photos/doctor/doctor_439342.jpg","hot":"1","level":"","sendSpCode":null,"reviewScore":"4","doctorsAttitude":"4","treatmentEffect":"4","favStatis":"","orderStatis":"","reviewStatis":"","hasResource":true,"schedules":[{"departmentCode":"","departmentName":"","doctorCode":"15_137","doctorName":"","scheDate":"2016-07-18","amPm":"上午","state":"0","freeNum":"0","returnMsg":"1","payType":"0"},{"departmentCode":"","departmentName":"","doctorCode":"15_137","doctorName":"","scheDate":"2016-07-21","amPm":"上午","state":"0","freeNum":"0","returnMsg":"1","payType":"0"}],"member":"DOCTOR_439342","score":0.0},{"hospitalId":"1775","hospitalName":"广东省第二中医院(白云院区)","departmentId":"215929","departmentName":"白云分院专家特需门诊","doctorId":"439343","doctorName":"靳利利","status":null,"spId":null,"spCode":null,"regSubject":"","verNum":null,"priority":null,"sex":"0","birthday":"","title":"主任中医师","fee":"","intro":"主任中医师 教授 医学博士 硕士研究生导师 ","specialty":"擅长心血管方面多种疾病的诊疗，如高血压病、冠心病、心律失常、动脉粥样硬化症、心功能不全、心肌炎、喘促、肢体麻木。","notice":"","photo":"http://183.63.133.156:8015/dl/photos/doctor/doctor_439343.jpg","hot":"1","level":"","sendSpCode":null,"reviewScore":"4","doctorsAttitude":"4","treatmentEffect":"4","favStatis":"","orderStatis":"","reviewStatis":"","hasResource":true,"schedules":[],"member":"DOCTOR_439343","score":0.0},{"hospitalId":"1775","hospitalName":"广东省第二中医院(白云院区)","departmentId":"215929","departmentName":"白云分院专家特需门诊","doctorId":"439344","doctorName":"高敏","status":null,"spId":null,"spCode":null,"regSubject":"","verNum":null,"priority":null,"sex":"0","birthday":"","title":"主任中医师","fee":"","intro":"主任中医师 教授 医学博士 硕士研究生导师 ","specialty":"擅长神经内科多种疾病的诊疗，如中风病、眩晕、失眠、焦虑抑郁症等心理疾病。","notice":"","photo":"http://183.63.133.156:8015/dl/photos/doctor/doctor_439344.jpg","hot":"1","level":"","sendSpCode":null,"reviewScore":"4","doctorsAttitude":"4","treatmentEffect":"4","favStatis":"","orderStatis":"","reviewStatis":"","hasResource":true,"schedules":[{"departmentCode":"","departmentName":"","doctorCode":"15_628","doctorName":"","scheDate":"2016-07-19","amPm":"上午","state":"0","freeNum":"0","returnMsg":"1","payType":"0"}],"member":"DOCTOR_439344","score":0.0},{"hospitalId":"1775","hospitalName":"广东省第二中医院(白云院区)","departmentId":"215929","departmentName":"白云分院专家特需门诊","doctorId":"439345","doctorName":"吕雄","status":null,"spId":null,"spCode":null,"regSubject":"","verNum":null,"priority":null,"sex":"1","birthday":"","title":"主任中医师","fee":"","intro":"主任中医师 教授 硕士研究生导师 ","specialty":"擅长内分泌方面常见疾病的诊疗，如糖尿病及并发症、甲状腺疾病、血脂异常及肥胖症。","notice":"","photo":"http://183.63.133.156:8015/dl/photos/doctor/doctor_439345.jpg","hot":"1","level":"","sendSpCode":null,"reviewScore":"4","doctorsAttitude":"4","treatmentEffect":"4","favStatis":"","orderStatis":"","reviewStatis":"","hasResource":true,"schedules":[{"departmentCode":"","departmentName":"","doctorCode":"15_657","doctorName":"","scheDate":"2016-07-20","amPm":"上午","state":"0","freeNum":"18","returnMsg":"1","payType":"0"}],"member":"DOCTOR_439345","score":0.0},{"hospitalId":"1775","hospitalName":"广东省第二中医院(白云院区)","departmentId":"215929","departmentName":"白云分院专家特需门诊","doctorId":"439346","doctorName":"陈宁","status":null,"spId":null,"spCode":null,"regSubject":"","verNum":null,"priority":null,"sex":"0","birthday":"","title":"主任中医师","fee":"","intro":"主任中医师 教授 硕士研究生导师 ","specialty":"擅长呼吸系统方面多种疾病的诊疗，如急慢性支气管炎、急慢性咽炎、慢阻肺疾病、哮喘、肺炎。","notice":"","photo":"http://183.63.133.156:8015/dl/photos/doctor/doctor_439346.jpg","hot":"1","level":"","sendSpCode":null,"reviewScore":"4","doctorsAttitude":"4","treatmentEffect":"4","favStatis":"","orderStatis":"","reviewStatis":"","hasResource":true,"schedules":[],"member":"DOCTOR_439346","score":0.0},{"hospitalId":"1775","hospitalName":"广东省第二中医院(白云院区)","departmentId":"215929","departmentName":"白云分院专家特需门诊","doctorId":"439347","doctorName":"余德钊","status":null,"spId":null,"spCode":null,"regSubject":"","verNum":null,"priority":null,"sex":"1","birthday":"","title":"主任中医师","fee":"","intro":"主任中医师 教授 硕士研究生导师 ","specialty":"擅长小儿常见疾病的诊疗，如小儿咳嗽、鼾证、急慢性胃炎、汗证,遗尿。","notice":"","photo":"http://183.63.133.156:8015/dl/photos/doctor/doctor_439347.jpg","hot":"1","level":"","sendSpCode":null,"reviewScore":"4","doctorsAttitude":"4","treatmentEffect":"4","favStatis":"","orderStatis":"","reviewStatis":"","hasResource":true,"schedules":[{"departmentCode":"","departmentName":"","doctorCode":"15_924","doctorName":"","scheDate":"2016-07-20","amPm":"下午","state":"0","freeNum":"0","returnMsg":"1","payType":"0"},{"departmentCode":"","departmentName":"","doctorCode":"15_924","doctorName":"","scheDate":"2016-07-23","amPm":"上午","state":"0","freeNum":"3","returnMsg":"1","payType":"0"}],"member":"DOCTOR_439347","score":0.0}],"sum":6,"days":["2016-07-17 星期日","2016-07-18 星期一","2016-07-19 星期二","2016-07-20 星期三","2016-07-21 星期四","2016-07-22 星期五","2016-07-23 星期六","2016-07-24 星期日"],"index":6}