{"resultCode":"0000","msg":"成功","response":[{"hospitalId":"1772","hospitalName":"广州市中医医院","departmentId":"215169","departmentName":"普通肾病科","doctorId":"430203","doctorName":"赵威","status":null,"spId":null,"spCode":null,"regSubject":"","verNum":null,"priority":null,"sex":"1","birthday":"","title":"主治医师","fee":"","intro":"毕业于广州中医药大学，硕士研究生擅于中西医结合治疗急慢性肾炎、急慢性肾衰竭、类风湿关节炎、强直性脊柱炎等肾脏及风湿性疾病。","specialty":"毕业于广州中医药大学，硕士研究生擅于中西医结合治疗急慢性肾炎、急慢性肾衰竭、类风湿关节炎、强直性脊柱炎等肾脏及风湿性疾病。","notice":"","photo":"http://183.63.133.156:8015/dl/photos/doctor/doctor_430203.jpg","hot":"1","level":"","sendSpCode":null,"reviewScore":"4","doctorsAttitude":"4","treatmentEffect":"4","favStatis":"","orderStatis":"","reviewStatis":"","hasResource":true,"schedules":[{"departmentCode":"","departmentName":"","doctorCode":"50_0099","doctorName":"","scheDate":"2016-07-19","amPm":"上午","state":"0","freeNum":"28","returnMsg":"1","payType":"0"},{"departmentCode":"","departmentName":"","doctorCode":"50_0099","doctorName":"","scheDate":"2016-07-21","amPm":"上午","state":"0","freeNum":"32","returnMsg":"1","payType":"0"},{"departmentCode":"","departmentName":"","doctorCode":"50_0099","doctorName":"","scheDate":"2016-07-26","amPm":"上午","state":"0","freeNum":"32","returnMsg":"1","payType":"0"},{"departmentCode":"","departmentName":"","doctorCode":"50_0099","doctorName":"","scheDate":"2016-07-28","amPm":"上午","state":"0","freeNum":"32","returnMsg":"1","payType":"0"}],"member":"DOCTOR_430203","score":0.0},{"hospitalId":"1772","hospitalName":"广州市中医医院","departmentId":"215169","departmentName":"普通肾病科","doctorId":"430204","doctorName":"于晓瑜","status":null,"spId":null,"spCode":null,"regSubject":"","verNum":null,"priority":null,"sex":"0","birthday":"","title":"主治医师","fee":"","intro":"2007年毕业于广州中医药大学，肾病硕士学位。擅于中西医结合治疗慢性肾功能衰竭、肾病综合征、狼疮性肾炎等肾内科常见病、多发病，擅长处理血液透析病人的急性、慢性并发症等。","specialty":"2007年毕业于广州中医药大学，肾病硕士学位。擅于中西医结合治疗慢性肾功能衰竭、肾病综合征、狼疮性肾炎等肾内科常见病、多发病，擅长处理血液透析病人的急性、慢性并发症等。","notice":"","photo":"http://183.63.133.156:8015/dl/photos/doctor/doctor_430204.jpg","hot":"1","level":"","sendSpCode":null,"reviewScore":"4","doctorsAttitude":"4","treatmentEffect":"4","favStatis":"","orderStatis":"","reviewStatis":"","hasResource":true,"schedules":[],"member":"DOCTOR_430204","score":0.0},{"hospitalId":"1772","hospitalName":"广州市中医医院","departmentId":"215169","departmentName":"普通肾病科","doctorId":"430205","doctorName":"陈家湄","status":null,"spId":null,"spCode":null,"regSubject":"","verNum":null,"priority":null,"sex":"0","birthday":"","title":"主治医师","fee":"","intro":"毕业于中山大学，硕士学历，熟练掌握肾内科慢性肾炎、肾病综合征、慢性肾衰竭、糖尿病肾病等多种常见病、多发病的诊断与治疗，擅长连续性肾脏替代治疗、血液灌流、血浆置换等多种血液净化模式的治疗运用及血液透析并发症等的处理。","specialty":"毕业于中山大学，硕士学历，熟练掌握肾内科慢性肾炎、肾病综合征、慢性肾衰竭、糖尿病肾病等多种常见病、多发病的诊断与治疗，擅长连续性肾脏替代治疗、血液灌流、血浆置换等多种血液净化模式的治疗运用及血液透析并发症等的处理。","notice":"","photo":"http://183.63.133.156:8015/dl/photos/doctor/doctor_430205.jpg","hot":"1","level":"","sendSpCode":null,"reviewScore":"4","doctorsAttitude":"4","treatmentEffect":"4","favStatis":"","orderStatis":"","reviewStatis":"","hasResource":true,"schedules":[{"departmentCode":"","departmentName":"","doctorCode":"50_1059","doctorName":"","scheDate":"2016-07-22","amPm":"下午","state":"0","freeNum":"24","returnMsg":"1","payType":"0"},{"departmentCode":"","departmentName":"","doctorCode":"50_1059","doctorName":"","scheDate":"2016-07-29","amPm":"下午","state":"0","freeNum":"24","returnMsg":"1","payType":"0"}],"member":"DOCTOR_430205","score":0.0},{"hospitalId":"1772","hospitalName":"广州市中医医院","departmentId":"215169","departmentName":"普通肾病科","doctorId":"430206","doctorName":"李娟","status":null,"spId":null,"spCode":null,"regSubject":"","verNum":null,"priority":null,"sex":"0","birthday":"","title":"主治医师","fee":"","intro":"擅长中西医结合治疗各种急性、慢性肾炎、良性动脉硬化肾病、糖尿病肾病、骨关节炎、类风湿性关节炎等。","specialty":"擅长中西医结合治疗各种急性、慢性肾炎、良性动脉硬化肾病、糖尿病肾病、骨关节炎、类风湿性关节炎等。","notice":"","photo":"http://183.63.133.156:8015/dl/photos/doctor/doctor_430206.jpg","hot":"1","level":"","sendSpCode":null,"reviewScore":"4","doctorsAttitude":"4","treatmentEffect":"4","favStatis":"","orderStatis":"","reviewStatis":"","hasResource":true,"schedules":[],"member":"DOCTOR_430206","score":0.0},{"hospitalId":"1772","hospitalName":"广州市中医医院","departmentId":"215169","departmentName":"普通肾病科","doctorId":"430207","doctorName":"俸维","status":null,"spId":null,"spCode":null,"regSubject":"","verNum":null,"priority":null,"sex":"0","birthday":"","title":"主治医师","fee":"","intro":"毕业于广州中医药大学，硕士学位。熟练运用中西医结合治疗慢行肾衰竭，肾病综合症及处理血液透析的常见并发症。","specialty":"毕业于广州中医药大学，硕士学位。熟练运用中西医结合治疗慢行肾衰竭，肾病综合症及处理血液透析的常见并发症。","notice":"","photo":"http://183.63.133.156:8015/dl/photos/doctor/doctor_430207.jpg","hot":"1","level":"","sendSpCode":null,"reviewScore":"4","doctorsAttitude":"4","treatmentEffect":"4","favStatis":"","orderStatis":"","reviewStatis":"","hasResource":true,"schedules":[{"departmentCode":"","departmentName":"","doctorCode":"50_1105","doctorName":"","scheDate":"2016-07-20","amPm":"下午","state":"0","freeNum":"24","returnMsg":"1","payType":"0"},{"departmentCode":"","departmentName":"","doctorCode":"50_1105","doctorName":"","scheDate":"2016-07-27","amPm":"下午","state":"0","freeNum":"24","returnMsg":"1","payType":"0"}],"member":"DOCTOR_430207","score":0.0},{"hospitalId":"1772","hospitalName":"广州市中医医院","departmentId":"215169","departmentName":"普通肾病科","doctorId":"430208","doctorName":"周艳利","status":null,"spId":null,"spCode":null,"regSubject":"","verNum":null,"priority":null,"sex":"0","birthday":"","title":"主治医师","fee":"","intro":"毕业于湖南中医药大学，硕士学历。2011年于湘雅二医院肾内科进修。熟悉肾内科慢性肾炎、肾病综合征、狼疮性肾炎、急慢性肾功能不全等多种常见病的诊断与治疗。熟悉腹膜透析、各种血液透析及血透相关并发症的处理。","specialty":"毕业于湖南中医药大学，硕士学历。2011年于湘雅二医院肾内科进修。熟悉肾内科慢性肾炎、肾病综合征、狼疮性肾炎、急慢性肾功能不全等多种常见病的诊断与治疗。熟悉腹膜透析、各种血液透析及血透相关并发症的处理。","notice":"","photo":"http://183.63.133.156:8015/dl/photos/doctor/doctor_430208.jpg","hot":"1","level":"","sendSpCode":null,"reviewScore":"4","doctorsAttitude":"4","treatmentEffect":"4","favStatis":"","orderStatis":"","reviewStatis":"","hasResource":true,"schedules":[{"departmentCode":"","departmentName":"","doctorCode":"50_1147","doctorName":"","scheDate":"2016-07-21","amPm":"下午","state":"0","freeNum":"0","returnMsg":"1","payType":"0"}],"member":"DOCTOR_430208","score":0.0},{"hospitalId":"1772","hospitalName":"广州市中医医院","departmentId":"215169","departmentName":"普通肾病科","doctorId":"430209","doctorName":"唐瑾秋","status":null,"spId":null,"spCode":null,"regSubject":"","verNum":null,"priority":null,"sex":"0","birthday":"","title":"主治医师","fee":"","intro":"暂无","specialty":"熟练掌握中西医结合治疗肾炎、泌尿系感染、痛风、风湿、干燥综合征等内科疾病。","notice":"","photo":"http://183.63.133.156:8015/dl/photos/doctor/doctor_430209.jpg","hot":"1","level":"","sendSpCode":null,"reviewScore":"4","doctorsAttitude":"4","treatmentEffect":"4","favStatis":"","orderStatis":"","reviewStatis":"","hasResource":true,"schedules":[{"departmentCode":"","departmentName":"","doctorCode":"50_1183","doctorName":"","scheDate":"2016-07-26","amPm":"下午","state":"0","freeNum":"24","returnMsg":"1","payType":"0"},{"departmentCode":"","departmentName":"","doctorCode":"50_1183","doctorName":"","scheDate":"2016-07-26","amPm":"夜诊","state":"0","freeNum":"24","returnMsg":"1","payType":"0"}],"member":"DOCTOR_430209","score":0.0},{"hospitalId":"1772","hospitalName":"广州市中医医院","departmentId":"215169","departmentName":"普通肾病科","doctorId":"430210","doctorName":"李季","status":null,"spId":null,"spCode":null,"regSubject":"","verNum":null,"priority":null,"sex":"1","birthday":"","title":"主治医师","fee":"","intro":"暂无","specialty":"毕业于广州中医药大学风湿病专业，医学硕士。熟练类风湿关节炎强直性脊柱炎、骨关节炎、狼疮性肾炎、肾功能不全等风湿免疫系统及肾病科疾病的中西医诊治。发表医学及教学论文8篇","notice":"","photo":"http://183.63.133.156:8015/dl/photos/doctor/doctor_430210.jpg","hot":"1","level":"","sendSpCode":null,"reviewScore":"4","doctorsAttitude":"4","treatmentEffect":"4","favStatis":"","orderStatis":"","reviewStatis":"","hasResource":true,"schedules":[],"member":"DOCTOR_430210","score":0.0}],"sum":8,"days":["2016-07-16 星期六","2016-07-17 星期日","2016-07-18 星期一","2016-07-19 星期二","2016-07-20 星期三","2016-07-21 星期四","2016-07-22 星期五","2016-07-23 星期六","2016-07-24 星期日","2016-07-25 星期一","2016-07-26 星期二","2016-07-27 星期三","2016-07-28 星期四","2016-07-29 星期五","2016-07-30 星期六"],"index":8}