{"resultCode":"0000","msg":"成功","response":[{"provinceId":"5","cityId":"63","areaId":"126","hospitalId":"794","hospitalName":"公安县人民医院","status":null,"spId":null,"spCode":null,"verNum":null,"priority":null,"member":"HOSPITAL_794","score":0.0},{"provinceId":"5","cityId":"63","areaId":"126","hospitalId":"792","hospitalName":"石首市第二医院","status":null,"spId":null,"spCode":null,"verNum":null,"priority":null,"member":"HOSPITAL_792","score":0.0},{"provinceId":"5","cityId":"63","areaId":"126","hospitalId":"791","hospitalName":"石首市人民医院","status":null,"spId":null,"spCode":null,"verNum":null,"priority":null,"member":"HOSPITAL_791","score":0.0},{"provinceId":"5","cityId":"63","areaId":"126","hospitalId":"789","hospitalName":"荆州市第三人民医院","status":null,"spId":null,"spCode":null,"verNum":null,"priority":null,"member":"HOSPITAL_789","score":0.0},{"provinceId":"5","cityId":"63","areaId":"126","hospitalId":"761","hospitalName":"荆州市第二人民医院","status":null,"spId":null,"spCode":null,"verNum":null,"priority":null,"member":"HOSPITAL_761","score":0.0},{"provinceId":"5","cityId":"63","areaId":"126","hospitalId":"756","hospitalName":"江陵县人民医院","status":null,"spId":null,"spCode":null,"verNum":null,"priority":null,"member":"HOSPITAL_756","score":0.0},{"provinceId":"5","cityId":"63","areaId":"126","hospitalId":"747","hospitalName":"荆州市妇幼保健院","status":null,"spId":null,"spCode":null,"verNum":null,"priority":null,"member":"HOSPITAL_747","score":0.0},{"provinceId":"5","cityId":"63","areaId":"126","hospitalId":"715","hospitalName":"荆州市中医院","status":null,"spId":null,"spCode":null,"verNum":null,"priority":null,"member":"HOSPITAL_715","score":0.0},{"provinceId":"5","cityId":"63","areaId":"126","hospitalId":"714","hospitalName":"荆州市中心医院","status":null,"spId":null,"spCode":null,"verNum":null,"priority":null,"member":"HOSPITAL_714","score":0.0},{"provinceId":"5","cityId":"63","areaId":"126","hospitalId":"713","hospitalName":"荆州市第一人民医院","status":null,"spId":null,"spCode":null,"verNum":null,"priority":null,"member":"HOSPITAL_713","score":0.0}]}{"resultCode":"0000","msg":"成功","response":[{"provinceId":"5","cityId":"63","areaId":"126","hospitalId":"794","hospitalName":"公安县人民医院","status":null,"spId":null,"spCode":null,"verNum":null,"priority":null,"member":"HOSPITAL_794","score":0.0},{"provinceId":"5","cityId":"63","areaId":"126","hospitalId":"792","hospitalName":"石首市第二医院","status":null,"spId":null,"spCode":null,"verNum":null,"priority":null,"member":"HOSPITAL_792","score":0.0},{"provinceId":"5","cityId":"63","areaId":"126","hospitalId":"791","hospitalName":"石首市人民医院","status":null,"spId":null,"spCode":null,"verNum":null,"priority":null,"member":"HOSPITAL_791","score":0.0},{"provinceId":"5","cityId":"63","areaId":"126","hospitalId":"789","hospitalName":"荆州市第三人民医院","status":null,"spId":null,"spCode":null,"verNum":null,"priority":null,"member":"HOSPITAL_789","score":0.0},{"provinceId":"5","cityId":"63","areaId":"126","hospitalId":"761","hospitalName":"荆州市第二人民医院","status":null,"spId":null,"spCode":null,"verNum":null,"priority":null,"member":"HOSPITAL_761","score":0.0},{"provinceId":"5","cityId":"63","areaId":"126","hospitalId":"756","hospitalName":"江陵县人民医院","status":null,"spId":null,"spCode":null,"verNum":null,"priority":null,"member":"HOSPITAL_756","score":0.0},{"provinceId":"5","cityId":"63","areaId":"126","hospitalId":"747","hospitalName":"荆州市妇幼保健院","status":null,"spId":null,"spCode":null,"verNum":null,"priority":null,"member":"HOSPITAL_747","score":0.0},{"provinceId":"5","cityId":"63","areaId":"126","hospitalId":"715","hospitalName":"荆州市中医院","status":null,"spId":null,"spCode":null,"verNum":null,"priority":null,"member":"HOSPITAL_715","score":0.0},{"provinceId":"5","cityId":"63","areaId":"126","hospitalId":"714","hospitalName":"荆州市中心医院","status":null,"spId":null,"spCode":null,"verNum":null,"priority":null,"member":"HOSPITAL_714","score":0.0},{"provinceId":"5","cityId":"63","areaId":"126","hospitalId":"713","hospitalName":"荆州市第一人民医院","status":null,"spId":null,"spCode":null,"verNum":null,"priority":null,"member":"HOSPITAL_713","score":0.0}]}