{"resultCode":"0000","msg":"成功","response":[{"hospitalId":"1050","hospitalName":"广东省中医院大学城医院","departmentId":"256908","departmentName":"肿瘤专科","doctorId":"685947","doctorName":"高蕾","status":null,"spId":null,"spCode":null,"regSubject":"","verNum":null,"priority":null,"sex":"0","birthday":"","title":"主任医师","fee":"","intro":"擅长：各种恶性肿瘤及部分良性疾病以放射治疗为主的中西医结合治疗。尤其是鼻咽癌三维适形及调强放疗、乳腺癌术后、宫颈癌、肺癌、食管癌、中枢神经系统、直肠癌、骨转移瘤以及甲亢突眼症、皮肤疤痕等良性病的放射治疗。","specialty":"擅长：各种恶性肿瘤及部分良性疾病以放射治疗为主的中西医结合治疗。尤其是鼻咽癌三维适形及调强放疗、乳腺癌术后、宫颈癌、肺癌、食管癌、中枢神经系统、直肠癌、骨转移瘤以及甲亢突眼症、皮肤疤痕等良性病的放射治疗。","notice":"","photo":"http://183.63.133.156:8015/dl/photos/doctor/doctor_685947.jpg","hot":"1","level":"","sendSpCode":null,"reviewScore":"4","doctorsAttitude":"4","treatmentEffect":"4","favStatis":"","orderStatis":"","reviewStatis":"","hasResource":true,"schedules":[{"departmentCode":"6001935302","departmentName":"","doctorCode":"35_60273","doctorName":"","scheDate":"2016-07-20","amPm":"上午","state":"0","freeNum":"30","returnMsg":"1","payType":"0"}],"member":"DOCTOR_685947","score":0.0},{"hospitalId":"1050","hospitalName":"广东省中医院大学城医院","departmentId":"256908","departmentName":"肿瘤专科","doctorId":"685948","doctorName":"李柳宁","status":null,"spId":null,"spCode":null,"regSubject":"","verNum":null,"priority":null,"sex":"0","birthday":"","title":"主任医师","fee":"","intro":"擅长：肺癌、肠癌、肝癌、乳腺癌、鼻咽癌、淋巴瘤等恶性肿瘤的中西医诊治，对肿瘤的术后抗复发、转移及放化疗减毒增效的中医药治疗有较深入研究；内科疑难杂病如急慢性咳喘、腹痛、腹泻、胃痛等的中西医结合诊治。","specialty":"擅长：肺癌、肠癌、肝癌、乳腺癌、鼻咽癌、淋巴瘤等恶性肿瘤的中西医诊治，对肿瘤的术后抗复发、转移及放化疗减毒增效的中医药治疗有较深入研究；内科疑难杂病如急慢性咳喘、腹痛、腹泻、胃痛等的中西医结合诊治。","notice":"","photo":"http://183.63.133.156:8015/dl/photos/doctor/doctor_685948.jpg","hot":"1","level":"","sendSpCode":null,"reviewScore":"4","doctorsAttitude":"4","treatmentEffect":"4","favStatis":"","orderStatis":"","reviewStatis":"","hasResource":true,"schedules":[{"departmentCode":"6001934098","departmentName":"","doctorCode":"35_1378","doctorName":"","scheDate":"2016-07-18","amPm":"上午","state":"0","freeNum":"0","returnMsg":"1","payType":"0"}],"member":"DOCTOR_685948","score":0.0},{"hospitalId":"1050","hospitalName":"广东省中医院大学城医院","departmentId":"256908","departmentName":"肿瘤专科","doctorId":"685950","doctorName":"陈志坚","status":null,"spId":null,"spCode":null,"regSubject":"","verNum":null,"priority":null,"sex":"1","birthday":"","title":"主治医师","fee":"","intro":"陈志坚，男，主治医师。2003年毕业于广州中医药大学，中医内科学硕士，熟练掌握中西医学基本理论应用于临床，主攻中西医结合肿瘤学，认真仔细致力于临床实践工作，参与多个科研课题及发表多篇医学论文。常见内科疾病的中西医诊治，擅长肺癌、肝癌、鼻咽癌、胃癌、肠癌、食道癌、淋巴瘤、乳腺癌、妇科肿瘤等各系统肿瘤中西医诊治。","specialty":"擅长肺癌、肝癌、肠癌的综合治疗，以及放化疗后中医药减毒治疗","notice":"","photo":"http://183.63.133.156:8015/dl/photos/doctor/doctor_685950.jpg","hot":"1","level":"","sendSpCode":null,"reviewScore":"4","doctorsAttitude":"4","treatmentEffect":"4","favStatis":"","orderStatis":"","reviewStatis":"","hasResource":true,"schedules":[{"departmentCode":"6001935318","departmentName":"","doctorCode":"35_61652","doctorName":"","scheDate":"2016-07-20","amPm":"下午","state":"0","freeNum":"24","returnMsg":"1","payType":"0"}],"member":"DOCTOR_685950","score":0.0},{"hospitalId":"1050","hospitalName":"广东省中医院大学城医院","departmentId":"256908","departmentName":"肿瘤专科","doctorId":"685951","doctorName":"高蕾","status":null,"spId":null,"spCode":null,"regSubject":"","verNum":null,"priority":null,"sex":"0","birthday":"","title":"主任医师","fee":"","intro":"擅长：各种恶性肿瘤及部分良性疾病以放射治疗为主的中西医结合治疗。尤其是鼻咽癌三维适形及调强放疗、乳腺癌术后、宫颈癌、肺癌、食管癌、中枢神经系统、直肠癌、骨转移瘤以及甲亢突眼症、皮肤疤痕等良性病的放射治疗。","specialty":"擅长：各种恶性肿瘤及部分良性疾病以放射治疗为主的中西医结合治疗。尤其是鼻咽癌三维适形及调强放疗、乳腺癌术后、宫颈癌、肺癌、食管癌、中枢神经系统、直肠癌、骨转移瘤以及甲亢突眼症、皮肤疤痕等良性病的放射治疗。","notice":"","photo":"http://183.63.133.156:8015/dl/photos/doctor/doctor_685951.jpg","hot":"1","level":"","sendSpCode":null,"reviewScore":"4","doctorsAttitude":"4","treatmentEffect":"4","favStatis":"","orderStatis":"","reviewStatis":"","hasResource":true,"schedules":[{"departmentCode":"6001935302","departmentName":"","doctorCode":"35_60273","doctorName":"","scheDate":"2016-07-20","amPm":"上午","state":"0","freeNum":"30","returnMsg":"1","payType":"0"}],"member":"DOCTOR_685951","score":0.0},{"hospitalId":"1050","hospitalName":"广东省中医院大学城医院","departmentId":"256908","departmentName":"肿瘤专科","doctorId":"685952","doctorName":"洪宏喜","status":null,"spId":null,"spCode":null,"regSubject":"","verNum":null,"priority":null,"sex":"1","birthday":"","title":"主治医师","fee":"","intro":"","specialty":"","notice":"","photo":"","hot":"1","level":"","sendSpCode":null,"reviewScore":"4","doctorsAttitude":"4","treatmentEffect":"4","favStatis":"","orderStatis":"","reviewStatis":"","hasResource":true,"schedules":[{"departmentCode":"6001936070","departmentName":"","doctorCode":"35_61986","doctorName":"","scheDate":"2016-07-21","amPm":"下午","state":"0","freeNum":"27","returnMsg":"1","payType":"0"}],"member":"DOCTOR_685952","score":0.0},{"hospitalId":"1050","hospitalName":"广东省中医院大学城医院","departmentId":"256908","departmentName":"肿瘤专科","doctorId":"685953","doctorName":"孔怡琳","status":null,"spId":null,"spCode":null,"regSubject":"","verNum":null,"priority":null,"sex":"0","birthday":"","title":"主治医师","fee":"","intro":"孔怡琳，女，主治医师，医学硕士，毕业于广州中医药大学。擅长鼻咽癌、肺癌、乳腺癌、食管癌、宫颈癌等各类恶性肿瘤的中西医结合治疗，善于运用中医药防治放化疗毒副作用，熟悉常见肿瘤并发症的处理。","specialty":"擅长鼻咽癌、肺癌、乳腺癌、食管癌、宫颈癌等各类恶性肿瘤的中西医结合治疗，善于运用中医药防治放化疗毒副作用，熟悉常见肿瘤并发症的处理。","notice":"","photo":"http://183.63.133.156:8015/dl/photos/doctor/doctor_685953.jpg","hot":"1","level":"","sendSpCode":null,"reviewScore":"4","doctorsAttitude":"4","treatmentEffect":"4","favStatis":"","orderStatis":"","reviewStatis":"","hasResource":true,"schedules":[{"departmentCode":"6001934341","departmentName":"","doctorCode":"35_61903","doctorName":"","scheDate":"2016-07-19","amPm":"下午","state":"0","freeNum":"45","returnMsg":"1","payType":"0"}],"member":"DOCTOR_685953","score":0.0},{"hospitalId":"1050","hospitalName":"广东省中医院大学城医院","departmentId":"256908","departmentName":"肿瘤专科","doctorId":"685954","doctorName":"刘柏","status":null,"spId":null,"spCode":null,"regSubject":"","verNum":null,"priority":null,"sex":"1","birthday":"","title":"主治医师","fee":"","intro":"刘柏，男，主治医师。2003年毕业于广州中医药大学，中医内科学硕士，熟练掌握中西医学基本理论应用于临床，主攻中西医结合肿瘤学，认真仔细致力于临床实践工作，参与多个科研课题及发表多篇医学论文。常见内科疾病的中西医诊治，擅长肺癌、肝癌、鼻咽癌、胃癌、肠癌、食道癌、淋巴瘤、乳腺癌、妇科肿瘤等各系统肿瘤中西医诊治。","specialty":"擅长： 常见内科疾病的中西医诊治，擅长肺癌、肝癌、鼻咽癌、胃癌、肠癌、食道癌、淋巴瘤、乳腺癌、妇科等各系统肿瘤中西医诊治","notice":"","photo":"http://183.63.133.156:8015/dl/photos/doctor/doctor_685954.jpg","hot":"1","level":"","sendSpCode":null,"reviewScore":"4","doctorsAttitude":"4","treatmentEffect":"4","favStatis":"","orderStatis":"","reviewStatis":"","hasResource":true,"schedules":[{"departmentCode":"6001936927","departmentName":"","doctorCode":"35_61773","doctorName":"","scheDate":"2016-07-22","amPm":"下午","state":"0","freeNum":"44","returnMsg":"1","payType":"0"}],"member":"DOCTOR_685954","score":0.0},{"hospitalId":"1050","hospitalName":"广东省中医院大学城医院","departmentId":"256908","departmentName":"肿瘤专科","doctorId":"685955","doctorName":"薛晓光","status":null,"spId":null,"spCode":null,"regSubject":"","verNum":null,"priority":null,"sex":"1","birthday":"","title":"主治医师","fee":"","intro":"擅长：各种良恶性肿瘤及并发症的中西医结合诊疗。如：肺癌、胃癌、肝癌、肠癌、乳腺癌、卵巢癌、鼻咽癌、食道癌、恶性淋巴瘤、多发性骨髓瘤等。对内科疑难疾病等有较丰富临床经验。","specialty":"擅长：各种良恶性肿瘤及并发症的中西医结合诊疗。如：肺癌、胃癌、肝癌、肠癌、乳腺癌、卵巢癌、鼻咽癌、食道癌、恶性淋巴瘤、多发性骨髓瘤等。对内科疑难疾病等有较丰富临床经验。","notice":"","photo":"http://183.63.133.156:8015/dl/photos/doctor/doctor_685955.jpg","hot":"1","level":"","sendSpCode":null,"reviewScore":"4","doctorsAttitude":"4","treatmentEffect":"4","favStatis":"","orderStatis":"","reviewStatis":"","hasResource":true,"schedules":[{"departmentCode":"6001934110","departmentName":"","doctorCode":"35_61378","doctorName":"","scheDate":"2016-07-18","amPm":"上午","state":"0","freeNum":"43","returnMsg":"1","payType":"0"}],"member":"DOCTOR_685955","score":0.0}],"sum":11,"days":["2016-07-16 星期六","2016-07-17 星期日","2016-07-18 星期一","2016-07-19 星期二","2016-07-20 星期三","2016-07-21 星期四","2016-07-22 星期五","2016-07-23 星期六","2016-07-24 星期日"],"index":8}