{"resultCode":"0000","msg":"成功","response":[{"hospitalId":"1050","hospitalName":"广东省中医院大学城医院","departmentId":"256903","departmentName":"消化专科","doctorId":"685929","doctorName":"黄绍刚","status":null,"spId":null,"spCode":null,"regSubject":"","verNum":null,"priority":null,"sex":"1","birthday":"","title":"主任医师","fee":"","intro":"擅长：消化科各种疑难病和常见病的中西医诊断治疗。如慢性胃炎、胃食管反流病、消化性溃疡、慢性便秘、慢性腹泻及肝胆胰腺等疾病。","specialty":"擅长：消化科各种疑难病和常见病的中西医诊断治疗。如慢性胃炎、胃食管反流病、消化性溃疡、慢性便秘、慢性腹泻及肝胆胰腺等疾病。","notice":"","photo":"http://183.63.133.156:8015/dl/photos/doctor/doctor_685929.jpg","hot":"1","level":"","sendSpCode":null,"reviewScore":"4","doctorsAttitude":"4","treatmentEffect":"4","favStatis":"","orderStatis":"","reviewStatis":"","hasResource":true,"schedules":[{"departmentCode":"6001934099","departmentName":"","doctorCode":"35_61244","doctorName":"","scheDate":"2016-07-18","amPm":"下午","state":"0","freeNum":"7","returnMsg":"1","payType":"0"},{"departmentCode":"6001934331","departmentName":"","doctorCode":"35_61244","doctorName":"","scheDate":"2016-07-19","amPm":"上午","state":"0","freeNum":"5","returnMsg":"1","payType":"0"},{"departmentCode":"6001936922","departmentName":"","doctorCode":"35_61244","doctorName":"","scheDate":"2016-07-22","amPm":"上午","state":"0","freeNum":"35","returnMsg":"1","payType":"0"}],"member":"DOCTOR_685929","score":0.0},{"hospitalId":"1050","hospitalName":"广东省中医院大学城医院","departmentId":"256903","departmentName":"消化专科","doctorId":"685930","doctorName":"陈君千","status":null,"spId":null,"spCode":null,"regSubject":"","verNum":null,"priority":null,"sex":"1","birthday":"","title":"主治医师","fee":"","intro":"","specialty":"","notice":"","photo":"","hot":"1","level":"","sendSpCode":null,"reviewScore":"4","doctorsAttitude":"4","treatmentEffect":"4","favStatis":"","orderStatis":"","reviewStatis":"","hasResource":true,"schedules":[{"departmentCode":"6001935326","departmentName":"","doctorCode":"35_62494","doctorName":"","scheDate":"2016-07-20","amPm":"下午","state":"0","freeNum":"25","returnMsg":"1","payType":"0"}],"member":"DOCTOR_685930","score":0.0},{"hospitalId":"1050","hospitalName":"广东省中医院大学城医院","departmentId":"256903","departmentName":"消化专科","doctorId":"685931","doctorName":"胡丽娟","status":null,"spId":null,"spCode":null,"regSubject":"","verNum":null,"priority":null,"sex":"0","birthday":"","title":"主治医师","fee":"","intro":"中西医结合诊疗内科常见疾病，尤其是消化系统疾病，如慢性胃炎、消化性溃疡、溃疡性结肠炎、反流性食管炎等，熟练掌握胃肠镜检查及镜下治疗。","specialty":"擅长中西医结合诊疗内科常见疾病，尤其是消化系统疾病，如慢性胃炎、消化性溃疡、溃疡性结肠炎、反流性食管炎等，熟练掌握胃肠镜检查及镜下治疗。","notice":"","photo":"http://183.63.133.156:8015/dl/photos/doctor/doctor_685931.jpg","hot":"1","level":"","sendSpCode":null,"reviewScore":"4","doctorsAttitude":"4","treatmentEffect":"4","favStatis":"","orderStatis":"","reviewStatis":"","hasResource":true,"schedules":[{"departmentCode":"6001932983","departmentName":"","doctorCode":"35_61336","doctorName":"","scheDate":"2016-07-16","amPm":"上午","state":"0","freeNum":"7","returnMsg":"1","payType":"0"},{"departmentCode":"6001934108","departmentName":"","doctorCode":"35_61336","doctorName":"","scheDate":"2016-07-18","amPm":"上午","state":"0","freeNum":"42","returnMsg":"1","payType":"0"},{"departmentCode":"6001934109","departmentName":"","doctorCode":"35_61336","doctorName":"","scheDate":"2016-07-18","amPm":"下午","state":"0","freeNum":"29","returnMsg":"1","payType":"0"},{"departmentCode":"6001934333","departmentName":"","doctorCode":"35_61336","doctorName":"","scheDate":"2016-07-19","amPm":"上午","state":"0","freeNum":"45","returnMsg":"1","payType":"0"},{"departmentCode":"6001934334","departmentName":"","doctorCode":"35_61336","doctorName":"","scheDate":"2016-07-19","amPm":"下午","state":"0","freeNum":"29","returnMsg":"1","payType":"0"},{"departmentCode":"6001935314","departmentName":"","doctorCode":"35_61336","doctorName":"","scheDate":"2016-07-20","amPm":"上午","state":"0","freeNum":"45","returnMsg":"1","payType":"0"},{"departmentCode":"6001936067","departmentName":"","doctorCode":"35_61336","doctorName":"","scheDate":"2016-07-21","amPm":"上午","state":"0","freeNum":"44","returnMsg":"1","payType":"0"},{"departmentCode":"6001936068","departmentName":"","doctorCode":"35_61336","doctorName":"","scheDate":"2016-07-21","amPm":"下午","state":"0","freeNum":"30","returnMsg":"1","payType":"0"},{"departmentCode":"6001936923","departmentName":"","doctorCode":"35_61336","doctorName":"","scheDate":"2016-07-22","amPm":"上午","state":"0","freeNum":"45","returnMsg":"1","payType":"0"},{"departmentCode":"6001936924","departmentName":"","doctorCode":"35_61336","doctorName":"","scheDate":"2016-07-22","amPm":"下午","state":"0","freeNum":"30","returnMsg":"1","payType":"0"},{"departmentCode":"6001937495","departmentName":"","doctorCode":"35_61336","doctorName":"","scheDate":"2016-07-23","amPm":"上午","state":"0","freeNum":"45","returnMsg":"1","payType":"0"}],"member":"DOCTOR_685931","score":0.0},{"hospitalId":"1050","hospitalName":"广东省中医院大学城医院","departmentId":"256903","departmentName":"消化专科","doctorId":"685932","doctorName":"黄绍刚","status":null,"spId":null,"spCode":null,"regSubject":"","verNum":null,"priority":null,"sex":"1","birthday":"","title":"主任医师","fee":"","intro":"擅长：消化科各种疑难病和常见病的中西医诊断治疗。如慢性胃炎、胃食管反流病、消化性溃疡、慢性便秘、慢性腹泻及肝胆胰腺等疾病。","specialty":"擅长：消化科各种疑难病和常见病的中西医诊断治疗。如慢性胃炎、胃食管反流病、消化性溃疡、慢性便秘、慢性腹泻及肝胆胰腺等疾病。","notice":"","photo":"http://183.63.133.156:8015/dl/photos/doctor/doctor_685932.jpg","hot":"1","level":"","sendSpCode":null,"reviewScore":"4","doctorsAttitude":"4","treatmentEffect":"4","favStatis":"","orderStatis":"","reviewStatis":"","hasResource":true,"schedules":[{"departmentCode":"6001934099","departmentName":"","doctorCode":"35_61244","doctorName":"","scheDate":"2016-07-18","amPm":"下午","state":"0","freeNum":"7","returnMsg":"1","payType":"0"},{"departmentCode":"6001934331","departmentName":"","doctorCode":"35_61244","doctorName":"","scheDate":"2016-07-19","amPm":"上午","state":"0","freeNum":"5","returnMsg":"1","payType":"0"},{"departmentCode":"6001936922","departmentName":"","doctorCode":"35_61244","doctorName":"","scheDate":"2016-07-22","amPm":"上午","state":"0","freeNum":"35","returnMsg":"1","payType":"0"}],"member":"DOCTOR_685932","score":0.0},{"hospitalId":"1050","hospitalName":"广东省中医院大学城医院","departmentId":"256903","departmentName":"消化专科","doctorId":"685933","doctorName":"张海燕","status":null,"spId":null,"spCode":null,"regSubject":"","verNum":null,"priority":null,"sex":"0","birthday":"","title":"副主任医师","fee":"","intro":"","specialty":"","notice":"","photo":"","hot":"1","level":"","sendSpCode":null,"reviewScore":"4","doctorsAttitude":"4","treatmentEffect":"4","favStatis":"","orderStatis":"","reviewStatis":"","hasResource":true,"schedules":[{"departmentCode":"6001934113","departmentName":"","doctorCode":"35_61737","doctorName":"","scheDate":"2016-07-18","amPm":"下午","state":"0","freeNum":"25","returnMsg":"1","payType":"0"}],"member":"DOCTOR_685933","score":0.0}],"sum":5,"days":["2016-07-16 星期六","2016-07-17 星期日","2016-07-18 星期一","2016-07-19 星期二","2016-07-20 星期三","2016-07-21 星期四","2016-07-22 星期五","2016-07-23 星期六","2016-07-24 星期日"],"index":5}