{"resultCode":"0000","msg":"成功","response":[{"hospitalId":"282","hospitalName":"广州军区广州总医院","departmentId":"9578","departmentName":"口腔科","doctorId":"40706","doctorName":"戴威林","status":null,"spId":null,"spCode":null,"regSubject":"","verNum":null,"priority":null,"sex":"1","birthday":"1970-01-01","title":"主管技师","fee":"","intro":"主管技师","specialty":"各类口腔牙列缺失的活动修复和固定修复;尤其对大型复杂的活动义齿修复有较高造诣。对青少年错合畸形的矫治有较深层次的掌握和经验;传统的矫治技术和现时先进的矫治方法能熟练结合应用于临床;擅长于各类牙列拥挤;反合的矫治和替牙期、乳牙期的早期正畸。","notice":"","photo":"http://183.63.133.156:8015/dl/photos/doctor/doctor_40706.jpg","hot":"1","level":"","sendSpCode":null,"reviewScore":"4","doctorsAttitude":"4","treatmentEffect":"4","favStatis":"1","orderStatis":"0","reviewStatis":"0","hasResource":true,"schedules":[],"member":"DOCTOR_40706","score":0.0},{"hospitalId":"282","hospitalName":"广州军区广州总医院","departmentId":"9578","departmentName":"口腔科","doctorId":"40707","doctorName":"匡威","status":null,"spId":null,"spCode":null,"regSubject":"","verNum":null,"priority":null,"sex":"1","birthday":"1970-01-01","title":"主治医师","fee":"","intro":"主治医师","specialty":"对口腔颌面部间隙感染、良恶性肿瘤、战创伤、颌面部骨折、颌骨畸形、涎腺疾病等有较丰富的临床诊治经验。","notice":"","photo":"http://183.63.133.156:8015/dl/photos/doctor/doctor_40707.jpg","hot":"1","level":"","sendSpCode":null,"reviewScore":"4","doctorsAttitude":"4","treatmentEffect":"4","favStatis":"2","orderStatis":"0","reviewStatis":"0","hasResource":true,"schedules":[],"member":"DOCTOR_40707","score":0.0},{"hospitalId":"282","hospitalName":"广州军区广州总医院","departmentId":"9578","departmentName":"口腔科","doctorId":"40708","doctorName":"李洪涛","status":null,"spId":null,"spCode":null,"regSubject":"","verNum":null,"priority":null,"sex":"1","birthday":"1970-01-01","title":"主治医师","fee":"","intro":"主治医师","specialty":"长牙体牙髓病、牙周病和口腔颌面外科各类疾病的诊断和治疗;尤其擅长治疗牙周疾病的牙周外科技术。","notice":"","photo":"http://183.63.133.156:8015/dl/photos/doctor/doctor_40708.jpg","hot":"1","level":"","sendSpCode":null,"reviewScore":"4","doctorsAttitude":"4","treatmentEffect":"4","favStatis":"1","orderStatis":"0","reviewStatis":"0","hasResource":true,"schedules":[],"member":"DOCTOR_40708","score":0.0},{"hospitalId":"282","hospitalName":"广州军区广州总医院","departmentId":"9578","departmentName":"口腔科","doctorId":"40709","doctorName":"王桥","status":null,"spId":null,"spCode":null,"regSubject":"","verNum":null,"priority":null,"sex":"1","birthday":"1970-01-01","title":"副主任","fee":"","intro":"副主任医师","specialty":"牙种植技术、颌面部肿瘤及创伤的诊断和治疗。","notice":"","photo":"http://183.63.133.156:8015/dl/photos/doctor/doctor_40709.jpg","hot":"1","level":"","sendSpCode":null,"reviewScore":"4","doctorsAttitude":"4","treatmentEffect":"4","favStatis":"","orderStatis":"","reviewStatis":"","hasResource":true,"schedules":[],"member":"DOCTOR_40709","score":0.0},{"hospitalId":"282","hospitalName":"广州军区广州总医院","departmentId":"9578","departmentName":"口腔科","doctorId":"40710","doctorName":"魏艳萍","status":null,"spId":null,"spCode":null,"regSubject":"","verNum":null,"priority":null,"sex":"0","birthday":"1970-01-01","title":"主治医师","fee":"","intro":"主治医师","specialty":"从事口腔临床工作多年;对活动义齿、固定义齿等修复技术有丰富的临床经验;擅长于运用精密附着体等新技术新方法进行义齿修复。","notice":"","photo":"http://183.63.133.156:8015/dl/photos/doctor/doctor_40710.jpg","hot":"1","level":"","sendSpCode":null,"reviewScore":"4","doctorsAttitude":"4","treatmentEffect":"4","favStatis":"","orderStatis":"","reviewStatis":"","hasResource":true,"schedules":[],"member":"DOCTOR_40710","score":0.0},{"hospitalId":"282","hospitalName":"广州军区广州总医院","departmentId":"9578","departmentName":"口腔科","doctorId":"40711","doctorName":"张毅","status":null,"spId":null,"spCode":null,"regSubject":"","verNum":null,"priority":null,"sex":"1","birthday":"1970-01-01","title":"主治医师","fee":"","intro":"主治医师","specialty":"牙体牙髓病、牙周病的临床治疗和牙齿缺失的美容修复。","notice":"","photo":"http://183.63.133.156:8015/dl/photos/doctor/doctor_40711.jpg","hot":"1","level":"","sendSpCode":null,"reviewScore":"4","doctorsAttitude":"4","treatmentEffect":"4","favStatis":"1","orderStatis":"0","reviewStatis":"0","hasResource":true,"schedules":[],"member":"DOCTOR_40711","score":0.0},{"hospitalId":"282","hospitalName":"广州军区广州总医院","departmentId":"9578","departmentName":"口腔科","doctorId":"40712","doctorName":"陈建雄","status":null,"spId":null,"spCode":null,"regSubject":"","verNum":null,"priority":null,"sex":"1","birthday":"1970-01-01","title":"副主任","fee":"","intro":"陈建雄;男;副主任医师;副教授","specialty":"肝癌外科续贯治疗、胆道外科手术、腹腔镜及微创外科手术、肝脏移植、门脉高压症的外科治疗、胰腺肿瘤外科治疗、重症胰腺炎内外科治疗等。在肝癌的射频治疗、介入治疗和无水酒精注射治疗、胆道镜治疗胆石症、胆道镜治疗各种瘘等独到之处。","notice":"","photo":"http://183.63.133.156:8015/dl/photos/doctor/doctor_40712.jpg","hot":"1","level":"","sendSpCode":null,"reviewScore":"4","doctorsAttitude":"4","treatmentEffect":"4","favStatis":"","orderStatis":"","reviewStatis":"","hasResource":true,"schedules":[],"member":"DOCTOR_40712","score":0.0},{"hospitalId":"282","hospitalName":"广州军区广州总医院","departmentId":"9578","departmentName":"口腔科","doctorId":"40700","doctorName":"普通医师","status":null,"spId":null,"spCode":null,"regSubject":"","verNum":null,"priority":null,"sex":"0","birthday":"","title":"主治医师","fee":"4","intro":"","specialty":"","notice":"","photo":"http://183.63.133.156:8015/dl/photos/doctor/doctor_40700.jpg","hot":"1","level":"5","sendSpCode":null,"reviewScore":"4","doctorsAttitude":"4","treatmentEffect":"4","favStatis":"1","orderStatis":"0","reviewStatis":"0","hasResource":true,"schedules":[],"member":"DOCTOR_40700","score":0.0}],"sum":13,"days":["2016-07-17 星期日","2016-07-18 星期一","2016-07-19 星期二","2016-07-20 星期三","2016-07-21 星期四","2016-07-22 星期五","2016-07-23 星期六","2016-07-24 星期日"],"index":8}