{"resultCode":"0000","msg":"成功","response":[{"hospitalId":"1118","hospitalName":"广州中医药大学第一附属医院（机场路）","departmentId":"199348","departmentName":"产科门诊","doctorId":"312705","doctorName":"陈宝艳","status":null,"spId":null,"spCode":null,"regSubject":"","verNum":null,"priority":null,"sex":"0","birthday":"","title":"主治医师","fee":"","intro":"陈宝艳;女;医学硕士;主治医师。毕业于哈尔滨医科大学;妇产科学硕士;研究方向为围产医学;参与多项省级课题研究。从事产科临床医疗工作十余年;掌握产科常见病及疑难病症的诊断、治疗;熟练掌握产科手术操作。在产前检查、产程监护、难产的处理、产后保健等方面有较好的临床经验;擅长高危妊娠、产科合并症、并发症的诊断和治疗。","specialty":"","notice":"","photo":"http://183.63.133.156:8015/dl/photos/doctor/doctor_11984.jpg","hot":"1","level":"","sendSpCode":null,"reviewScore":"4","doctorsAttitude":"4","treatmentEffect":"4","favStatis":"","orderStatis":"","reviewStatis":"","hasResource":true,"schedules":[{"departmentCode":"44_0001310","departmentName":"产科门诊","doctorCode":"44_03664","doctorName":"陈宝艳","scheDate":"2016-07-18","amPm":"上午","state":"0","freeNum":"0","returnMsg":"1|1|1|1|1|1|1|1|1|1|1|1|1|1|1|1|1|1|1|1|1|1|1|1|1|1|1|1","payType":"0"},{"departmentCode":"44_0001310","departmentName":"产科门诊","doctorCode":"44_03664","doctorName":"陈宝艳","scheDate":"2016-07-19","amPm":"上午","state":"0","freeNum":"0","returnMsg":"1|1|1|1|1|1|1|1|1|1|1|1|1|1|1|1|1|1|1|1|1|1|1|1|1|1|1|1","payType":"0"}],"member":"DOCTOR_312705","score":0.0},{"hospitalId":"1118","hospitalName":"广州中医药大学第一附属医院（机场路）","departmentId":"199348","departmentName":"产科门诊","doctorId":"312706","doctorName":"黄敏珊","status":null,"spId":null,"spCode":null,"regSubject":"","verNum":null,"priority":null,"sex":"0","birthday":"","title":"主治医师","fee":"","intro":"黄敏珊;女;主治医师","specialty":"","notice":"","photo":"http://183.63.133.156:8015/dl/photos/doctor/doctor_11982.jpg","hot":"1","level":"","sendSpCode":null,"reviewScore":"4","doctorsAttitude":"4","treatmentEffect":"4","favStatis":"","orderStatis":"","reviewStatis":"","hasResource":true,"schedules":[],"member":"DOCTOR_312706","score":0.0},{"hospitalId":"1118","hospitalName":"广州中医药大学第一附属医院（机场路）","departmentId":"199348","departmentName":"产科门诊","doctorId":"312707","doctorName":"柯晓燕","status":null,"spId":null,"spCode":null,"regSubject":"","verNum":null,"priority":null,"sex":"0","birthday":"","title":"主治医师","fee":"","intro":"","specialty":"暂无","notice":"","photo":"","hot":"1","level":"","sendSpCode":null,"reviewScore":"4","doctorsAttitude":"4","treatmentEffect":"4","favStatis":"","orderStatis":"","reviewStatis":"","hasResource":true,"schedules":[],"member":"DOCTOR_312707","score":0.0},{"hospitalId":"1118","hospitalName":"广州中医药大学第一附属医院（机场路）","departmentId":"199348","departmentName":"产科门诊","doctorId":"312708","doctorName":"李道成","status":null,"spId":null,"spCode":null,"regSubject":"","verNum":null,"priority":null,"sex":"1","birthday":"","title":"教授/主任医师","fee":"","intro":"李道成;男;产科主任;主任医师;教授;医学博士;中西医结合妇产科硕士导师;广东省中西医结合学会妇产科专业委员会常委。本科毕业于同济医科大学;硕士毕业于中山医科大学（师从著名的妇科肿瘤专家梁立治教授）;博士毕业于广州中医药大学（师从著名的中医妇科专家罗颂平教授）。研究方向：优生优育;高危妊娠及妇科肿瘤的中西医结合治疗。产科方面：擅长高危妊娠（如：妊娠高血压、糖尿病、妊娠合并肿瘤、前置胎盘、胎儿生长发育受限、羊水过少、羊水过多等）的诊断和治疗;擅长子痫、产后出血、羊水栓塞、DIC等危、急重症的救治;擅长复杂的产科手术。妇科方面：擅长妇科良、恶性肿瘤的诊断与治疗。熟练掌握妇科肿瘤的诊断和治疗规范;熟练进行子宫内膜癌、宫颈癌、卵巢癌、外阴癌根治术等高难度的妇科手术;手术以精细、快捷见长;诊治水平达到省内先进水平。强调对肿瘤患者的微创治疗;擅长腹腔镜、宫腔镜手术和阴式手术;根据患者的具体情况选择合理的手术方式。中西医结合方面：擅长发挥中医、中药的优势;治疗妊娠期的合并症及并发症;预防产后抑郁等并发症的发生;促进产后康复及哺乳。中药治疗肿瘤;尽量避免手术;促进手术后康复。","specialty":"高危妊娠、急重症的救治、优生、妇科恶性肿瘤、尿失禁、内窥镜。","notice":"","photo":"http://183.63.133.156:8015/dl/photos/doctor/doctor_11981.jpg","hot":"1","level":"","sendSpCode":null,"reviewScore":"4","doctorsAttitude":"4","treatmentEffect":"4","favStatis":"","orderStatis":"","reviewStatis":"","hasResource":true,"schedules":[{"departmentCode":"44_0001310","departmentName":"产科门诊","doctorCode":"44_03070","doctorName":"李道成","scheDate":"2016-07-20","amPm":"上午","state":"0","freeNum":"0","returnMsg":"1|1|1|1|1|1|1|1|1|1|1|1|1|1|1|1|1|1|1|1|1|1|1|1|1|1|1|1|1|1|1|1|1|1|1|1|1|1|1","payType":"0"},{"departmentCode":"44_0001310","departmentName":"产科门诊","doctorCode":"44_03070","doctorName":"李道成","scheDate":"2016-07-21","amPm":"下午","state":"0","freeNum":"0","returnMsg":"1|1|1|1|1|1|1|1|1|1|1|1|1|1|1|1|1|1|1|1|1|1|1|1|1|1|1|1|1","payType":"0"}],"member":"DOCTOR_312708","score":0.0},{"hospitalId":"1118","hospitalName":"广州中医药大学第一附属医院（机场路）","departmentId":"199348","departmentName":"产科门诊","doctorId":"312709","doctorName":"李相宜","status":null,"spId":null,"spCode":null,"regSubject":"","verNum":null,"priority":null,"sex":"1","birthday":"","title":"主任医师","fee":"","intro":"","specialty":"暂无","notice":"","photo":"http://183.63.133.156:8015/dl/photos/doctor/doctor_71287.jpg","hot":"1","level":"","sendSpCode":null,"reviewScore":"4","doctorsAttitude":"4","treatmentEffect":"4","favStatis":"","orderStatis":"","reviewStatis":"","hasResource":true,"schedules":[{"departmentCode":"44_0001310","departmentName":"产科门诊","doctorCode":"44_03748","doctorName":"李相宜","scheDate":"2016-07-17","amPm":"上午","state":"0","freeNum":"0","returnMsg":"1|1|1|1|1|1|1|1|1|1|1|1|1|1|1|1|1|1|1","payType":"0"},{"departmentCode":"44_0001310","departmentName":"产科门诊","doctorCode":"44_03748","doctorName":"李相宜","scheDate":"2016-07-18","amPm":"上午","state":"0","freeNum":"0","returnMsg":"1|1|1|1|1|1|1|1|1|1|1|1|1|1|1|1|1|1|1","payType":"0"},{"departmentCode":"44_0001310","departmentName":"产科门诊","doctorCode":"44_03748","doctorName":"李相宜","scheDate":"2016-07-18","amPm":"下午","state":"0","freeNum":"0","returnMsg":"1|1|1|1|1|1|1|1|1|1|1|1|1|1","payType":"0"},{"departmentCode":"44_0001310","departmentName":"产科门诊","doctorCode":"44_03748","doctorName":"李相宜","scheDate":"2016-07-19","amPm":"上午","state":"0","freeNum":"0","returnMsg":"1|1|1|1|1|1|1|1|1|1|1|1|1|1|1|1|1|1|1","payType":"0"},{"departmentCode":"44_0001310","departmentName":"产科门诊","doctorCode":"44_03748","doctorName":"李相宜","scheDate":"2016-07-19","amPm":"下午","state":"0","freeNum":"0","returnMsg":"1|1|1|1|1|1|1|1|1|1|1|1|1|1","payType":"0"},{"departmentCode":"44_0001310","departmentName":"产科门诊","doctorCode":"44_03748","doctorName":"李相宜","scheDate":"2016-07-20","amPm":"上午","state":"0","freeNum":"0","returnMsg":"1|1|1|1|1|1|1|1|1|1|1|1|1|1|1|1|1|1|1","payType":"0"},{"departmentCode":"44_0001310","departmentName":"产科门诊","doctorCode":"44_03748","doctorName":"李相宜","scheDate":"2016-07-20","amPm":"下午","state":"0","freeNum":"0","returnMsg":"1|1|1|1|1|1|1|1|1|1|1|1|1|1","payType":"0"},{"departmentCode":"44_0001310","departmentName":"产科门诊","doctorCode":"44_03748","doctorName":"李相宜","scheDate":"2016-07-21","amPm":"上午","state":"0","freeNum":"0","returnMsg":"1|1|1|1|1|1|1|1|1|1|1|1|1|1|1|1|1|1|1","payType":"0"},{"departmentCode":"44_0001310","departmentName":"产科门诊","doctorCode":"44_03748","doctorName":"李相宜","scheDate":"2016-07-22","amPm":"上午","state":"0","freeNum":"0","returnMsg":"1|1|1|1|1|1|1|1|1|1|1|1|1|1|1|1|1|1|1","payType":"0"},{"departmentCode":"44_0001310","departmentName":"产科门诊","doctorCode":"44_03748","doctorName":"李相宜","scheDate":"2016-07-22","amPm":"下午","state":"0","freeNum":"0","returnMsg":"1|1|1|1|1|1|1|1|1|1|1|1|1|1","payType":"0"}],"member":"DOCTOR_312709","score":0.0},{"hospitalId":"1118","hospitalName":"广州中医药大学第一附属医院（机场路）","departmentId":"199348","departmentName":"产科门诊","doctorId":"312710","doctorName":"李艳芳","status":null,"spId":null,"spCode":null,"regSubject":"","verNum":null,"priority":null,"sex":"-1","birthday":"","title":"主治医师","fee":"","intro":"主治医师;硕士研究生。2001年本科毕业于中山医科大学;2008年取得香港大学公共卫生硕士研究生学位。从事妇产科工作多年;在孕期监护和处理方面有较丰富的临床经验;擅长产科常见病的诊治、妊娠合并症和妊娠并发症等高危妊娠的调理诊治;以及重症孕产妇的救治。曾在国家级专业刊物发表论文多篇。","specialty":"","notice":"","photo":"http://183.63.133.156:8015/dl/photos/doctor/doctor_11983.jpg","hot":"1","level":"","sendSpCode":null,"reviewScore":"4","doctorsAttitude":"4","treatmentEffect":"4","favStatis":"","orderStatis":"","reviewStatis":"","hasResource":true,"schedules":[],"member":"DOCTOR_312710","score":0.0},{"hospitalId":"1118","hospitalName":"广州中医药大学第一附属医院（机场路）","departmentId":"199348","departmentName":"产科门诊","doctorId":"312711","doctorName":"孙晓峰","status":null,"spId":null,"spCode":null,"regSubject":"","verNum":null,"priority":null,"sex":"0","birthday":"","title":"教授","fee":"","intro":"孙晓峰;女;主任医师;教授;医学硕士;硕士导师;广州市科技评审专家;广东省医学会医疗事故技术鉴定委员会围产医学组专家。本科就读于白求恩医科大学临床医疗系;毕业后在广东省妇幼保健院妇产科工作;2009年调往广州中医药大学第一附属医院产科;一直从事妇产科的临床、教学、科研工作。","specialty":"主要擅长于各种高危妊娠的诊断和处理;特别是妊娠合并内科疾病;如高血压、糖尿病、肾病、心脏病、甲亢、红斑狼疮等疾病的中西医治疗及监护方面有着深入的研究。另外在优生遗传诊治及产科多普勒超声技术方面有较多的临床经验。","notice":"","photo":"http://183.63.133.156:8015/dl/photos/doctor/doctor_11985.jpg","hot":"1","level":"","sendSpCode":null,"reviewScore":"4","doctorsAttitude":"4","treatmentEffect":"4","favStatis":"","orderStatis":"","reviewStatis":"","hasResource":true,"schedules":[{"departmentCode":"44_0001310","departmentName":"产科门诊","doctorCode":"44_03698","doctorName":"孙晓峰","scheDate":"2016-07-18","amPm":"上午","state":"0","freeNum":"0","returnMsg":"1|1|1|1|1|1|1|1|1|1|1|1|1|1|1|1|1|1|1|1","payType":"0"},{"departmentCode":"44_0001310","departmentName":"产科门诊","doctorCode":"44_03698","doctorName":"孙晓峰","scheDate":"2016-07-19","amPm":"下午","state":"0","freeNum":"0","returnMsg":"1|1|1|1|1|1|1|1|1|1|1|1|1|1","payType":"0"},{"departmentCode":"44_0001310","departmentName":"产科门诊","doctorCode":"44_03698","doctorName":"孙晓峰","scheDate":"2016-07-22","amPm":"上午","state":"0","freeNum":"0","returnMsg":"1|1|1|1|1|1|1|1|1|1|1|1|1|1|1|1|1|1|1|1","payType":"0"}],"member":"DOCTOR_312711","score":0.0},{"hospitalId":"1118","hospitalName":"广州中医药大学第一附属医院（机场路）","departmentId":"199348","departmentName":"产科门诊","doctorId":"312712","doctorName":"孙雪","status":null,"spId":null,"spCode":null,"regSubject":"","verNum":null,"priority":null,"sex":"0","birthday":"","title":"副主任医师 ","fee":"","intro":"","specialty":"","notice":"","photo":"","hot":"1","level":"","sendSpCode":null,"reviewScore":"4","doctorsAttitude":"4","treatmentEffect":"4","favStatis":"","orderStatis":"","reviewStatis":"","hasResource":true,"schedules":[],"member":"DOCTOR_312712","score":0.0}],"sum":12,"days":["2016-07-16 星期六","2016-07-17 星期日","2016-07-18 星期一","2016-07-19 星期二","2016-07-20 星期三","2016-07-21 星期四","2016-07-22 星期五","2016-07-23 星期六","2016-07-24 星期日","2016-07-25 星期一","2016-07-26 星期二","2016-07-27 星期三","2016-07-28 星期四","2016-07-29 星期五","2016-07-30 星期六","2016-07-31 星期日","2016-08-01 星期一","2016-08-02 星期二","2016-08-03 星期三","2016-08-04 星期四","2016-08-05 星期五","2016-08-06 星期六","2016-08-07 星期日","2016-08-08 星期一","2016-08-09 星期二","2016-08-10 星期三","2016-08-11 星期四","2016-08-12 星期五","2016-08-13 星期六","2016-08-14 星期日","2016-08-15 星期一","2016-08-16 星期二","2016-08-17 星期三"],"index":8}