{"resultCode":"0000","msg":"成功","response":[{"hospitalId":"399","departmentId":"26901","departmentName":"内科门诊","status":null,"standDeptId":"0","standDeptName":"","spId":null,"spCode":null,"verNum":null,"priority":null,"member":"DEPARTMENT_26901","score":0.0},{"hospitalId":"399","departmentId":"26936","departmentName":"普通内科2门诊","status":null,"standDeptId":"0","standDeptName":"","spId":null,"spCode":null,"verNum":null,"priority":null,"member":"DEPARTMENT_26936","score":0.0},{"hospitalId":"399","departmentId":"26828","departmentName":"离退休职工保健门诊","status":null,"standDeptId":"0","standDeptName":"","spId":null,"spCode":null,"verNum":null,"priority":null,"member":"DEPARTMENT_26828","score":0.0},{"hospitalId":"399","departmentId":"26960","departmentName":"血液内科门诊","status":null,"standDeptId":"0","standDeptName":"","spId":null,"spCode":null,"verNum":null,"priority":null,"member":"DEPARTMENT_26960","score":0.0},{"hospitalId":"399","departmentId":"26824","departmentName":"血液科慢性髓性白血病门诊","status":null,"standDeptId":"0","standDeptName":"","spId":null,"spCode":null,"verNum":null,"priority":null,"member":"DEPARTMENT_26824","score":0.0},{"hospitalId":"399","departmentId":"26954","departmentName":"血液内科2门诊","status":null,"standDeptId":"0","standDeptName":"","spId":null,"spCode":null,"verNum":null,"priority":null,"member":"DEPARTMENT_26954","score":0.0},{"hospitalId":"399","departmentId":"26978","departmentName":"呼吸内科门诊","status":null,"standDeptId":"0","standDeptName":"","spId":null,"spCode":null,"verNum":null,"priority":null,"member":"DEPARTMENT_26978","score":0.0},{"hospitalId":"399","departmentId":"26990","departmentName":"呼吸内科2门诊","status":null,"standDeptId":"0","standDeptName":"","spId":null,"spCode":null,"verNum":null,"priority":null,"member":"DEPARTMENT_26990","score":0.0},{"hospitalId":"399","departmentId":"26948","departmentName":"疾病鉴定门诊","status":null,"standDeptId":"0","standDeptName":"","spId":null,"spCode":null,"verNum":null,"priority":null,"member":"DEPARTMENT_26948","score":0.0},{"hospitalId":"399","departmentId":"26907","departmentName":"肾内科门诊","status":null,"standDeptId":"0","standDeptName":"","spId":null,"spCode":null,"verNum":null,"priority":null,"member":"DEPARTMENT_26907","score":0.0},{"hospitalId":"399","departmentId":"26814","departmentName":"肾内科肾病综合征门诊","status":null,"standDeptId":"0","standDeptName":"","spId":null,"spCode":null,"verNum":null,"priority":null,"member":"DEPARTMENT_26814","score":0.0},{"hospitalId":"399","departmentId":"26815","departmentName":"肾内科IgA肾病门诊","status":null,"standDeptId":"0","standDeptName":"","spId":null,"spCode":null,"verNum":null,"priority":null,"member":"DEPARTMENT_26815","score":0.0},{"hospitalId":"399","departmentId":"26817","departmentName":"肾内科狼疮性肾炎门诊","status":null,"standDeptId":"0","standDeptName":"","spId":null,"spCode":null,"verNum":null,"priority":null,"member":"DEPARTMENT_26817","score":0.0},{"hospitalId":"399","departmentId":"26816","departmentName":"肾内科糖尿病肾病门诊","status":null,"standDeptId":"0","standDeptName":"","spId":null,"spCode":null,"verNum":null,"priority":null,"member":"DEPARTMENT_26816","score":0.0},{"hospitalId":"399","departmentId":"26810","departmentName":"肾内科腹膜透析门诊","status":null,"standDeptId":"0","standDeptName":"","spId":null,"spCode":null,"verNum":null,"priority":null,"member":"DEPARTMENT_26810","score":0.0},{"hospitalId":"399","departmentId":"26848","departmentName":"肾内科2门诊","status":null,"standDeptId":"0","standDeptName":"","spId":null,"spCode":null,"verNum":null,"priority":null,"member":"DEPARTMENT_26848","score":0.0},{"hospitalId":"399","departmentId":"26930","departmentName":"风湿内科门诊","status":null,"standDeptId":"0","standDeptName":"","spId":null,"spCode":null,"verNum":null,"priority":null,"member":"DEPARTMENT_26930","score":0.0},{"hospitalId":"399","departmentId":"26993","departmentName":"风湿科骨质疏松门诊","status":null,"standDeptId":"0","standDeptName":"","spId":null,"spCode":null,"verNum":null,"priority":null,"member":"DEPARTMENT_26993","score":0.0},{"hospitalId":"399","departmentId":"26871","departmentName":"消化内科门诊","status":null,"standDeptId":"0","standDeptName":"","spId":null,"spCode":null,"verNum":null,"priority":null,"member":"DEPARTMENT_26871","score":0.0},{"hospitalId":"399","departmentId":"26869","departmentName":"胃肠肝胆胰专科门诊","status":null,"standDeptId":"0","standDeptName":"","spId":null,"spCode":null,"verNum":null,"priority":null,"member":"DEPARTMENT_26869","score":0.0},{"hospitalId":"399","departmentId":"26905","departmentName":"消化科脂肪肝门诊","status":null,"standDeptId":"0","standDeptName":"","spId":null,"spCode":null,"verNum":null,"priority":null,"member":"DEPARTMENT_26905","score":0.0},{"hospitalId":"399","departmentId":"26890","departmentName":"胃食管返流病门诊","status":null,"standDeptId":"0","standDeptName":"","spId":null,"spCode":null,"verNum":null,"priority":null,"member":"DEPARTMENT_26890","score":0.0},{"hospitalId":"399","departmentId":"26951","departmentName":"消化科炎症性肠病专科门诊","status":null,"standDeptId":"0","standDeptName":"","spId":null,"spCode":null,"verNum":null,"priority":null,"member":"DEPARTMENT_26951","score":0.0},{"hospitalId":"399","departmentId":"26944","departmentName":"消化内镜门诊","status":null,"standDeptId":"0","standDeptName":"","spId":null,"spCode":null,"verNum":null,"priority":null,"member":"DEPARTMENT_26944","score":0.0},{"hospitalId":"399","departmentId":"27000","departmentName":"内分泌糖尿病门诊","status":null,"standDeptId":"0","standDeptName":"","spId":null,"spCode":null,"verNum":null,"priority":null,"member":"DEPARTMENT_27000","score":0.0},{"hospitalId":"399","departmentId":"26830","departmentName":"内分泌骨质疏松科门诊","status":null,"standDeptId":"0","standDeptName":"","spId":null,"spCode":null,"verNum":null,"priority":null,"member":"DEPARTMENT_26830","score":0.0},{"hospitalId":"399","departmentId":"26807","departmentName":"糖尿病护理门诊","status":null,"standDeptId":"0","standDeptName":"","spId":null,"spCode":null,"verNum":null,"priority":null,"member":"DEPARTMENT_26807","score":0.0},{"hospitalId":"399","departmentId":"26886","departmentName":"神经内科门诊","status":null,"standDeptId":"0","standDeptName":"","spId":null,"spCode":null,"verNum":null,"priority":null,"member":"DEPARTMENT_26886","score":0.0},{"hospitalId":"399","departmentId":"26889","departmentName":"神经内科2门诊","status":null,"standDeptId":"0","standDeptName":"","spId":null,"spCode":null,"verNum":null,"priority":null,"member":"DEPARTMENT_26889","score":0.0},{"hospitalId":"399","departmentId":"26937","departmentName":"高压氧门诊","status":null,"standDeptId":"0","standDeptName":"","spId":null,"spCode":null,"verNum":null,"priority":null,"member":"DEPARTMENT_26937","score":0.0},{"hospitalId":"399","departmentId":"26985","departmentName":"肝胆内科门诊","status":null,"standDeptId":"0","standDeptName":"","spId":null,"spCode":null,"verNum":null,"priority":null,"member":"DEPARTMENT_26985","score":0.0},{"hospitalId":"399","departmentId":"26850","departmentName":"核医学门诊","status":null,"standDeptId":"0","standDeptName":"","spId":null,"spCode":null,"verNum":null,"priority":null,"member":"DEPARTMENT_26850","score":0.0},{"hospitalId":"399","departmentId":"26879","departmentName":"外科门诊","status":null,"standDeptId":"0","standDeptName":"","spId":null,"spCode":null,"verNum":null,"priority":null,"member":"DEPARTMENT_26879","score":0.0},{"hospitalId":"399","departmentId":"26906","departmentName":"肝胆胰外科门诊","status":null,"standDeptId":"0","standDeptName":"","spId":null,"spCode":null,"verNum":null,"priority":null,"member":"DEPARTMENT_26906","score":0.0},{"hospitalId":"399","departmentId":"26903","departmentName":"肝胆胰外科胆石症门诊","status":null,"standDeptId":"0","standDeptName":"","spId":null,"spCode":null,"verNum":null,"priority":null,"member":"DEPARTMENT_26903","score":0.0},{"hospitalId":"399","departmentId":"26913","departmentName":"泌尿外科门诊","status":null,"standDeptId":"0","standDeptName":"","spId":null,"spCode":null,"verNum":null,"priority":null,"member":"DEPARTMENT_26913","score":0.0},{"hospitalId":"399","departmentId":"26918","departmentName":"男性科门诊","status":null,"standDeptId":"0","standDeptName":"","spId":null,"spCode":null,"verNum":null,"priority":null,"member":"DEPARTMENT_26918","score":0.0},{"hospitalId":"399","departmentId":"26969","departmentName":"肾移植门诊","status":null,"standDeptId":"0","standDeptName":"","spId":null,"spCode":null,"verNum":null,"priority":null,"member":"DEPARTMENT_26969","score":0.0},{"hospitalId":"399","departmentId":"26875","departmentName":"疼痛门诊","status":null,"standDeptId":"0","standDeptName":"","spId":null,"spCode":null,"verNum":null,"priority":null,"member":"DEPARTMENT_26875","score":0.0},{"hospitalId":"399","departmentId":"26827","departmentName":"烧伤科瘢痕治疗门诊","status":null,"standDeptId":"0","standDeptName":"","spId":null,"spCode":null,"verNum":null,"priority":null,"member":"DEPARTMENT_26827","score":0.0},{"hospitalId":"399","departmentId":"26825","departmentName":"骨科门诊","status":null,"standDeptId":"0","standDeptName":"","spId":null,"spCode":null,"verNum":null,"priority":null,"member":"DEPARTMENT_26825","score":0.0},{"hospitalId":"399","departmentId":"26826","departmentName":"骨科运动损伤门诊","status":null,"standDeptId":"0","standDeptName":"","spId":null,"spCode":null,"verNum":null,"priority":null,"member":"DEPARTMENT_26826","score":0.0},{"hospitalId":"399","departmentId":"26934","departmentName":"整形周围血管外科门诊","status":null,"standDeptId":"0","standDeptName":"","spId":null,"spCode":null,"verNum":null,"priority":null,"member":"DEPARTMENT_26934","score":0.0},{"hospitalId":"399","departmentId":"26996","departmentName":"胃肠外科门诊","status":null,"standDeptId":"0","standDeptName":"","spId":null,"spCode":null,"verNum":null,"priority":null,"member":"DEPARTMENT_26996","score":0.0},{"hospitalId":"399","departmentId":"26973","departmentName":"血管甲状腺腹壁疝外科门诊","status":null,"standDeptId":"0","standDeptName":"","spId":null,"spCode":null,"verNum":null,"priority":null,"member":"DEPARTMENT_26973","score":0.0},{"hospitalId":"399","departmentId":"26941","departmentName":"胸外科门诊","status":null,"standDeptId":"0","standDeptName":"","spId":null,"spCode":null,"verNum":null,"priority":null,"member":"DEPARTMENT_26941","score":0.0},{"hospitalId":"399","departmentId":"26914","departmentName":"胸外科胸腔镜门诊","status":null,"standDeptId":"0","standDeptName":"","spId":null,"spCode":null,"verNum":null,"priority":null,"member":"DEPARTMENT_26914","score":0.0},{"hospitalId":"399","departmentId":"26992","departmentName":"脑外科门诊","status":null,"standDeptId":"0","standDeptName":"","spId":null,"spCode":null,"verNum":null,"priority":null,"member":"DEPARTMENT_26992","score":0.0},{"hospitalId":"399","departmentId":"26970","departmentName":"造口护理门诊","status":null,"standDeptId":"0","standDeptName":"","spId":null,"spCode":null,"verNum":null,"priority":null,"member":"DEPARTMENT_26970","score":0.0},{"hospitalId":"399","departmentId":"26979","departmentName":"心理精神科门诊","status":null,"standDeptId":"0","standDeptName":"","spId":null,"spCode":null,"verNum":null,"priority":null,"member":"DEPARTMENT_26979","score":0.0},{"hospitalId":"399","departmentId":"26884","departmentName":"失眠门诊","status":null,"standDeptId":"0","standDeptName":"","spId":null,"spCode":null,"verNum":null,"priority":null,"member":"DEPARTMENT_26884","score":0.0},{"hospitalId":"399","departmentId":"26867","departmentName":"少儿心理(多动症)门诊","status":null,"standDeptId":"0","standDeptName":"","spId":null,"spCode":null,"verNum":null,"priority":null,"member":"DEPARTMENT_26867","score":0.0},{"hospitalId":"399","departmentId":"26861","departmentName":"焦虑抑郁门诊","status":null,"standDeptId":"0","standDeptName":"","spId":null,"spCode":null,"verNum":null,"priority":null,"member":"DEPARTMENT_26861","score":0.0},{"hospitalId":"399","departmentId":"26872","departmentName":"心理精神戒烟门诊","status":null,"standDeptId":"0","standDeptName":"","spId":null,"spCode":null,"verNum":null,"priority":null,"member":"DEPARTMENT_26872","score":0.0},{"hospitalId":"399","departmentId":"26893","departmentName":"妇科门诊","status":null,"standDeptId":"0","standDeptName":"","spId":null,"spCode":null,"verNum":null,"priority":null,"member":"DEPARTMENT_26893","score":0.0},{"hospitalId":"399","departmentId":"26950","departmentName":"产科门诊","status":null,"standDeptId":"0","standDeptName":"","spId":null,"spCode":null,"verNum":null,"priority":null,"member":"DEPARTMENT_26950","score":0.0},{"hospitalId":"399","departmentId":"26947","departmentName":"遗传优生咨询门诊","status":null,"standDeptId":"0","standDeptName":"","spId":null,"spCode":null,"verNum":null,"priority":null,"member":"DEPARTMENT_26947","score":0.0},{"hospitalId":"399","departmentId":"26987","departmentName":"产科产后保健门诊","status":null,"standDeptId":"0","standDeptName":"","spId":null,"spCode":null,"verNum":null,"priority":null,"member":"DEPARTMENT_26987","score":0.0},{"hospitalId":"399","departmentId":"26971","departmentName":"生殖助孕专科门诊","status":null,"standDeptId":"0","standDeptName":"","spId":null,"spCode":null,"verNum":null,"priority":null,"member":"DEPARTMENT_26971","score":0.0},{"hospitalId":"399","departmentId":"26964","departmentName":"生殖助孕男科门诊","status":null,"standDeptId":"0","standDeptName":"","spId":null,"spCode":null,"verNum":null,"priority":null,"member":"DEPARTMENT_26964","score":0.0},{"hospitalId":"399","departmentId":"26991","departmentName":"儿科门诊","status":null,"standDeptId":"0","standDeptName":"","spId":null,"spCode":null,"verNum":null,"priority":null,"member":"DEPARTMENT_26991","score":0.0},{"hospitalId":"399","departmentId":"26863","departmentName":"儿童发育与行为专科门诊","status":null,"standDeptId":"0","standDeptName":"","spId":null,"spCode":null,"verNum":null,"priority":null,"member":"DEPARTMENT_26863","score":0.0},{"hospitalId":"399","departmentId":"26888","departmentName":"儿童保健门诊","status":null,"standDeptId":"0","standDeptName":"","spId":null,"spCode":null,"verNum":null,"priority":null,"member":"DEPARTMENT_26888","score":0.0},{"hospitalId":"399","departmentId":"26942","departmentName":"小儿呼吸专科门诊","status":null,"standDeptId":"0","standDeptName":"","spId":null,"spCode":null,"verNum":null,"priority":null,"member":"DEPARTMENT_26942","score":0.0},{"hospitalId":"399","departmentId":"26995","departmentName":"小儿神经专科门诊","status":null,"standDeptId":"0","standDeptName":"","spId":null,"spCode":null,"verNum":null,"priority":null,"member":"DEPARTMENT_26995","score":0.0},{"hospitalId":"399","departmentId":"26920","departmentName":"小儿癫痫专科门诊","status":null,"standDeptId":"0","standDeptName":"","spId":null,"spCode":null,"verNum":null,"priority":null,"member":"DEPARTMENT_26920","score":0.0},{"hospitalId":"399","departmentId":"26847","departmentName":"儿科内分泌门诊","status":null,"standDeptId":"0","standDeptName":"","spId":null,"spCode":null,"verNum":null,"priority":null,"member":"DEPARTMENT_26847","score":0.0},{"hospitalId":"399","departmentId":"26868","departmentName":"新生儿门诊","status":null,"standDeptId":"0","standDeptName":"","spId":null,"spCode":null,"verNum":null,"priority":null,"member":"DEPARTMENT_26868","score":0.0},{"hospitalId":"399","departmentId":"26984","departmentName":"儿科肾病、风湿病门诊","status":null,"standDeptId":"0","standDeptName":"","spId":null,"spCode":null,"verNum":null,"priority":null,"member":"DEPARTMENT_26984","score":0.0},{"hospitalId":"399","departmentId":"26808","departmentName":"血液肿瘤儿科门诊","status":null,"standDeptId":"0","standDeptName":"","spId":null,"spCode":null,"verNum":null,"priority":null,"member":"DEPARTMENT_26808","score":0.0},{"hospitalId":"399","departmentId":"26845","departmentName":"中医科门诊","status":null,"standDeptId":"0","standDeptName":"","spId":null,"spCode":null,"verNum":null,"priority":null,"member":"DEPARTMENT_26845","score":0.0},{"hospitalId":"399","departmentId":"26822","departmentName":"中医妇儿门诊","status":null,"standDeptId":"0","standDeptName":"","spId":null,"spCode":null,"verNum":null,"priority":null,"member":"DEPARTMENT_26822","score":0.0},{"hospitalId":"399","departmentId":"26823","departmentName":"中医肿瘤门诊","status":null,"standDeptId":"0","standDeptName":"","spId":null,"spCode":null,"verNum":null,"priority":null,"member":"DEPARTMENT_26823","score":0.0},{"hospitalId":"399","departmentId":"26908","departmentName":"正骨科门诊","status":null,"standDeptId":"0","standDeptName":"","spId":null,"spCode":null,"verNum":null,"priority":null,"member":"DEPARTMENT_26908","score":0.0},{"hospitalId":"399","departmentId":"26900","departmentName":"康复医学科门诊","status":null,"standDeptId":"0","standDeptName":"","spId":null,"spCode":null,"verNum":null,"priority":null,"member":"DEPARTMENT_26900","score":0.0},{"hospitalId":"399","departmentId":"26832","departmentName":"皮肤、性病科门诊","status":null,"standDeptId":"0","standDeptName":"","spId":null,"spCode":null,"verNum":null,"priority":null,"member":"DEPARTMENT_26832","score":0.0},{"hospitalId":"399","departmentId":"26809","departmentName":"皮肤科激光治疗美容门诊","status":null,"standDeptId":"0","standDeptName":"","spId":null,"spCode":null,"verNum":null,"priority":null,"member":"DEPARTMENT_26809","score":0.0},{"hospitalId":"399","departmentId":"26842","departmentName":"皮肤科脱发门诊","status":null,"standDeptId":"0","standDeptName":"","spId":null,"spCode":null,"verNum":null,"priority":null,"member":"DEPARTMENT_26842","score":0.0},{"hospitalId":"399","departmentId":"26968","departmentName":"内分泌科2门诊","status":null,"standDeptId":"0","standDeptName":"","spId":null,"spCode":null,"verNum":null,"priority":null,"member":"DEPARTMENT_26968","score":0.0},{"hospitalId":"399","departmentId":"26933","departmentName":"呼吸科戒烟门诊","status":null,"standDeptId":"0","standDeptName":"","spId":null,"spCode":null,"verNum":null,"priority":null,"member":"DEPARTMENT_26933","score":0.0},{"hospitalId":"399","departmentId":"26902","departmentName":"烧伤科门诊","status":null,"standDeptId":"0","standDeptName":"","spId":null,"spCode":null,"verNum":null,"priority":null,"member":"DEPARTMENT_26902","score":0.0},{"hospitalId":"399","departmentId":"26873","departmentName":"营养内科门诊","status":null,"standDeptId":"0","standDeptName":"","spId":null,"spCode":null,"verNum":null,"priority":null,"member":"DEPARTMENT_26873","score":0.0},{"hospitalId":"399","departmentId":"26841","departmentName":"皮肤科白癜风门诊","status":null,"standDeptId":"0","standDeptName":"","spId":null,"spCode":null,"verNum":null,"priority":null,"member":"DEPARTMENT_26841","score":0.0},{"hospitalId":"399","departmentId":"26962","departmentName":"耳鼻喉科门诊","status":null,"standDeptId":"0","standDeptName":"","spId":null,"spCode":null,"verNum":null,"priority":null,"member":"DEPARTMENT_26962","score":0.0},{"hospitalId":"399","departmentId":"26870","departmentName":"眼科门诊","status":null,"standDeptId":"0","standDeptName":"","spId":null,"spCode":null,"verNum":null,"priority":null,"member":"DEPARTMENT_26870","score":0.0},{"hospitalId":"399","departmentId":"26831","departmentName":"眼视光学(近视角膜塑形验配)门诊","status":null,"standDeptId":"0","standDeptName":"","spId":null,"spCode":null,"verNum":null,"priority":null,"member":"DEPARTMENT_26831","score":0.0},{"hospitalId":"399","departmentId":"26804","departmentName":"屈光近视准分子门诊","status":null,"standDeptId":"0","standDeptName":"","spId":null,"spCode":null,"verNum":null,"priority":null,"member":"DEPARTMENT_26804","score":0.0},{"hospitalId":"399","departmentId":"26975","departmentName":"白内障专科门诊","status":null,"standDeptId":"0","standDeptName":"","spId":null,"spCode":null,"verNum":null,"priority":null,"member":"DEPARTMENT_26975","score":0.0},{"hospitalId":"399","departmentId":"26839","departmentName":"眼科青光眼门诊","status":null,"standDeptId":"0","standDeptName":"","spId":null,"spCode":null,"verNum":null,"priority":null,"member":"DEPARTMENT_26839","score":0.0},{"hospitalId":"399","departmentId":"26999","departmentName":"验光配镜专科门诊","status":null,"standDeptId":"0","standDeptName":"","spId":null,"spCode":null,"verNum":null,"priority":null,"member":"DEPARTMENT_26999","score":0.0},{"hospitalId":"399","departmentId":"26891","departmentName":"口腔科门诊","status":null,"standDeptId":"0","standDeptName":"","spId":null,"spCode":null,"verNum":null,"priority":null,"member":"DEPARTMENT_26891","score":0.0},{"hospitalId":"399","departmentId":"26813","departmentName":"口腔牙周病门诊","status":null,"standDeptId":"0","standDeptName":"","spId":null,"spCode":null,"verNum":null,"priority":null,"member":"DEPARTMENT_26813","score":0.0},{"hospitalId":"399","departmentId":"26812","departmentName":"口腔正畸门诊","status":null,"standDeptId":"0","standDeptName":"","spId":null,"spCode":null,"verNum":null,"priority":null,"member":"DEPARTMENT_26812","score":0.0},{"hospitalId":"399","departmentId":"26818","departmentName":"口腔种植牙门诊","status":null,"standDeptId":"0","standDeptName":"","spId":null,"spCode":null,"verNum":null,"priority":null,"member":"DEPARTMENT_26818","score":0.0},{"hospitalId":"399","departmentId":"26819","departmentName":"口腔修复门诊","status":null,"standDeptId":"0","standDeptName":"","spId":null,"spCode":null,"verNum":null,"priority":null,"member":"DEPARTMENT_26819","score":0.0},{"hospitalId":"399","departmentId":"26820","departmentName":"口腔颌面外科门诊","status":null,"standDeptId":"0","standDeptName":"","spId":null,"spCode":null,"verNum":null,"priority":null,"member":"DEPARTMENT_26820","score":0.0},{"hospitalId":"399","departmentId":"26834","departmentName":"疑难病会诊门诊","status":null,"standDeptId":"0","standDeptName":"","spId":null,"spCode":null,"verNum":null,"priority":null,"member":"DEPARTMENT_26834","score":0.0},{"hospitalId":"399","departmentId":"26843","departmentName":"内分泌糖尿病疑难病会诊门诊","status":null,"standDeptId":"0","standDeptName":"","spId":null,"spCode":null,"verNum":null,"priority":null,"member":"DEPARTMENT_26843","score":0.0},{"hospitalId":"399","departmentId":"26840","departmentName":"消化内科疑难病会诊门诊","status":null,"standDeptId":"0","standDeptName":"","spId":null,"spCode":null,"verNum":null,"priority":null,"member":"DEPARTMENT_26840","score":0.0},{"hospitalId":"399","departmentId":"26949","departmentName":"血液病疑难病会诊门诊","status":null,"standDeptId":"0","standDeptName":"","spId":null,"spCode":null,"verNum":null,"priority":null,"member":"DEPARTMENT_26949","score":0.0},{"hospitalId":"399","departmentId":"26938","departmentName":"骨髓移植科门诊","status":null,"standDeptId":"0","standDeptName":"","spId":null,"spCode":null,"verNum":null,"priority":null,"member":"DEPARTMENT_26938","score":0.0},{"hospitalId":"399","departmentId":"26966","departmentName":"普通科间会诊门诊","status":null,"standDeptId":"0","standDeptName":"","spId":null,"spCode":null,"verNum":null,"priority":null,"member":"DEPARTMENT_26966","score":0.0},{"hospitalId":"399","departmentId":"32714","departmentName":"心内科门诊（心研所）","status":null,"standDeptId":"0","standDeptName":"","spId":null,"spCode":null,"verNum":null,"priority":null,"member":"DEPARTMENT_32714","score":0.0},{"hospitalId":"399","departmentId":"32715","departmentName":"心外科门诊（心研所）","status":null,"standDeptId":"0","standDeptName":"","spId":null,"spCode":null,"verNum":null,"priority":null,"member":"DEPARTMENT_32715","score":0.0},{"hospitalId":"399","departmentId":"32716","departmentName":"心儿科门诊（心研所）","status":null,"standDeptId":"0","standDeptName":"","spId":null,"spCode":null,"verNum":null,"priority":null,"member":"DEPARTMENT_32716","score":0.0},{"hospitalId":"399","departmentId":"32717","departmentName":"心康复门诊（心研所）","status":null,"standDeptId":"0","standDeptName":"","spId":null,"spCode":null,"verNum":null,"priority":null,"member":"DEPARTMENT_32717","score":0.0},{"hospitalId":"399","departmentId":"32713","departmentName":"心中医科门诊（心研所）","status":null,"standDeptId":"0","standDeptName":"","spId":null,"spCode":null,"verNum":null,"priority":null,"member":"DEPARTMENT_32713","score":0.0},{"hospitalId":"399","departmentId":"26925","departmentName":"东病区心血管内科门诊","status":null,"standDeptId":"0","standDeptName":"","spId":null,"spCode":null,"verNum":null,"priority":null,"member":"DEPARTMENT_26925","score":0.0},{"hospitalId":"399","departmentId":"26946","departmentName":"东病区普通内科门诊","status":null,"standDeptId":"0","standDeptName":"","spId":null,"spCode":null,"verNum":null,"priority":null,"member":"DEPARTMENT_26946","score":0.0},{"hospitalId":"399","departmentId":"26972","departmentName":"东病区普外科门诊","status":null,"standDeptId":"0","standDeptName":"","spId":null,"spCode":null,"verNum":null,"priority":null,"member":"DEPARTMENT_26972","score":0.0},{"hospitalId":"399","departmentId":"26916","departmentName":"东病区骨外科门诊","status":null,"standDeptId":"0","standDeptName":"","spId":null,"spCode":null,"verNum":null,"priority":null,"member":"DEPARTMENT_26916","score":0.0},{"hospitalId":"399","departmentId":"26940","departmentName":"东病区妇科门诊","status":null,"standDeptId":"0","standDeptName":"","spId":null,"spCode":null,"verNum":null,"priority":null,"member":"DEPARTMENT_26940","score":0.0},{"hospitalId":"399","departmentId":"26878","departmentName":"东病区眼科门诊","status":null,"standDeptId":"0","standDeptName":"","spId":null,"spCode":null,"verNum":null,"priority":null,"member":"DEPARTMENT_26878","score":0.0},{"hospitalId":"399","departmentId":"26897","departmentName":"东病区耳鼻喉科门诊","status":null,"standDeptId":"0","standDeptName":"","spId":null,"spCode":null,"verNum":null,"priority":null,"member":"DEPARTMENT_26897","score":0.0},{"hospitalId":"399","departmentId":"26958","departmentName":"东病区中医科门诊","status":null,"standDeptId":"0","standDeptName":"","spId":null,"spCode":null,"verNum":null,"priority":null,"member":"DEPARTMENT_26958","score":0.0},{"hospitalId":"399","departmentId":"26894","departmentName":"东病区呼吸睡眠门诊","status":null,"standDeptId":"0","standDeptName":"","spId":null,"spCode":null,"verNum":null,"priority":null,"member":"DEPARTMENT_26894","score":0.0},{"hospitalId":"399","departmentId":"26929","departmentName":"东病区消化内科门诊","status":null,"standDeptId":"0","standDeptName":"","spId":null,"spCode":null,"verNum":null,"priority":null,"member":"DEPARTMENT_26929","score":0.0},{"hospitalId":"399","departmentId":"26983","departmentName":"东病区呼吸内科门诊","status":null,"standDeptId":"0","standDeptName":"","spId":null,"spCode":null,"verNum":null,"priority":null,"member":"DEPARTMENT_26983","score":0.0},{"hospitalId":"399","departmentId":"26892","departmentName":"东病区神经内科门诊","status":null,"standDeptId":"0","standDeptName":"","spId":null,"spCode":null,"verNum":null,"priority":null,"member":"DEPARTMENT_26892","score":0.0},{"hospitalId":"399","departmentId":"26956","departmentName":"东病区内分泌门诊","status":null,"standDeptId":"0","standDeptName":"","spId":null,"spCode":null,"verNum":null,"priority":null,"member":"DEPARTMENT_26956","score":0.0},{"hospitalId":"399","departmentId":"26851","departmentName":"东病区康复医学科门诊","status":null,"standDeptId":"0","standDeptName":"","spId":null,"spCode":null,"verNum":null,"priority":null,"member":"DEPARTMENT_26851","score":0.0},{"hospitalId":"399","departmentId":"26915","departmentName":"东病区肿瘤科门诊","status":null,"standDeptId":"0","standDeptName":"","spId":null,"spCode":null,"verNum":null,"priority":null,"member":"DEPARTMENT_26915","score":0.0},{"hospitalId":"399","departmentId":"26939","departmentName":"东病区皮肤科门诊","status":null,"standDeptId":"0","standDeptName":"","spId":null,"spCode":null,"verNum":null,"priority":null,"member":"DEPARTMENT_26939","score":0.0},{"hospitalId":"399","departmentId":"26877","departmentName":"东病区泌尿内科门诊","status":null,"standDeptId":"0","standDeptName":"","spId":null,"spCode":null,"verNum":null,"priority":null,"member":"DEPARTMENT_26877","score":0.0},{"hospitalId":"399","departmentId":"26854","departmentName":"东病区骨质疏松门诊","status":null,"standDeptId":"0","standDeptName":"","spId":null,"spCode":null,"verNum":null,"priority":null,"member":"DEPARTMENT_26854","score":0.0},{"hospitalId":"399","departmentId":"26927","departmentName":"东病区糖尿病门诊","status":null,"standDeptId":"0","standDeptName":"","spId":null,"spCode":null,"verNum":null,"priority":null,"member":"DEPARTMENT_26927","score":0.0},{"hospitalId":"399","departmentId":"26910","departmentName":"东病区中医高血压门诊","status":null,"standDeptId":"0","standDeptName":"","spId":null,"spCode":null,"verNum":null,"priority":null,"member":"DEPARTMENT_26910","score":0.0},{"hospitalId":"399","departmentId":"26855","departmentName":"东病区关节疼痛科门诊","status":null,"standDeptId":"0","standDeptName":"","spId":null,"spCode":null,"verNum":null,"priority":null,"member":"DEPARTMENT_26855","score":0.0},{"hospitalId":"399","departmentId":"26882","departmentName":"东病区慢性咳嗽哮喘科门诊","status":null,"standDeptId":"0","standDeptName":"","spId":null,"spCode":null,"verNum":null,"priority":null,"member":"DEPARTMENT_26882","score":0.0},{"hospitalId":"399","departmentId":"26846","departmentName":"东病区双心门诊","status":null,"standDeptId":"0","standDeptName":"","spId":null,"spCode":null,"verNum":null,"priority":null,"member":"DEPARTMENT_26846","score":0.0},{"hospitalId":"399","departmentId":"26932","departmentName":"东病区记忆障碍专科门诊","status":null,"standDeptId":"0","standDeptName":"","spId":null,"spCode":null,"verNum":null,"priority":null,"member":"DEPARTMENT_26932","score":0.0},{"hospitalId":"399","departmentId":"26986","departmentName":"东病区前列腺增生专家门诊","status":null,"standDeptId":"0","standDeptName":"","spId":null,"spCode":null,"verNum":null,"priority":null,"member":"DEPARTMENT_26986","score":0.0},{"hospitalId":"399","departmentId":"26799","departmentName":"东病区便秘门诊","status":null,"standDeptId":"0","standDeptName":"","spId":null,"spCode":null,"verNum":null,"priority":null,"member":"DEPARTMENT_26799","score":0.0},{"hospitalId":"399","departmentId":"26802","departmentName":"东病区慢阻肺(COPD)门诊","status":null,"standDeptId":"0","standDeptName":"","spId":null,"spCode":null,"verNum":null,"priority":null,"member":"DEPARTMENT_26802","score":0.0},{"hospitalId":"399","departmentId":"26829","departmentName":"东病区离退休职工保健门诊","status":null,"standDeptId":"0","standDeptName":"","spId":null,"spCode":null,"verNum":null,"priority":null,"member":"DEPARTMENT_26829","score":0.0},{"hospitalId":"399","departmentId":"26838","departmentName":"东病区消化内镜门诊","status":null,"standDeptId":"0","standDeptName":"","spId":null,"spCode":null,"verNum":null,"priority":null,"member":"DEPARTMENT_26838","score":0.0},{"hospitalId":"399","departmentId":"26800","departmentName":"东病区内分泌科骨质疏松门诊","status":null,"standDeptId":"0","standDeptName":"","spId":null,"spCode":null,"verNum":null,"priority":null,"member":"DEPARTMENT_26800","score":0.0},{"hospitalId":"399","departmentId":"46315","departmentName":"肿瘤科门诊","status":null,"standDeptId":"0","standDeptName":"","spId":null,"spCode":null,"verNum":null,"priority":null,"member":"DEPARTMENT_46315","score":0.0},{"hospitalId":"399","departmentId":"46314","departmentName":"胃肠肿瘤门诊","status":null,"standDeptId":"0","standDeptName":"","spId":null,"spCode":null,"verNum":null,"priority":null,"member":"DEPARTMENT_46314","score":0.0},{"hospitalId":"399","departmentId":"46313","departmentName":"胸部肿瘤门诊","status":null,"standDeptId":"0","standDeptName":"","spId":null,"spCode":null,"verNum":null,"priority":null,"member":"DEPARTMENT_46313","score":0.0},{"hospitalId":"399","departmentId":"46312","departmentName":"乳腺门诊","status":null,"standDeptId":"0","standDeptName":"","spId":null,"spCode":null,"verNum":null,"priority":null,"member":"DEPARTMENT_46312","score":0.0},{"hospitalId":"399","departmentId":"46308","departmentName":"东病区三号楼门诊","status":null,"standDeptId":"0","standDeptName":"","spId":null,"spCode":null,"verNum":null,"priority":null,"member":"DEPARTMENT_46308","score":0.0},{"hospitalId":"399","departmentId":"46305","departmentName":"放疗科门诊","status":null,"standDeptId":"0","standDeptName":"","spId":null,"spCode":null,"verNum":null,"priority":null,"member":"DEPARTMENT_46305","score":0.0},{"hospitalId":"399","departmentId":"46303","departmentName":"心射频、起博随访门诊","status":null,"standDeptId":"0","standDeptName":"","spId":null,"spCode":null,"verNum":null,"priority":null,"member":"DEPARTMENT_46303","score":0.0},{"hospitalId":"399","departmentId":"46302","departmentName":"疑难病超声会诊门诊","status":null,"standDeptId":"0","standDeptName":"","spId":null,"spCode":null,"verNum":null,"priority":null,"member":"DEPARTMENT_46302","score":0.0},{"hospitalId":"399","departmentId":"46301","departmentName":"省干部体检中心","status":null,"standDeptId":"0","standDeptName":"","spId":null,"spCode":null,"verNum":null,"priority":null,"member":"DEPARTMENT_46301","score":0.0},{"hospitalId":"399","departmentId":"46300","departmentName":"广东省老研所","status":null,"standDeptId":"0","standDeptName":"","spId":null,"spCode":null,"verNum":null,"priority":null,"member":"DEPARTMENT_46300","score":0.0},{"hospitalId":"399","departmentId":"46296","departmentName":"心内科高血压门诊","status":null,"standDeptId":"0","standDeptName":"","spId":null,"spCode":null,"verNum":null,"priority":null,"member":"DEPARTMENT_46296","score":0.0},{"hospitalId":"399","departmentId":"46293","departmentName":"静脉导管维护门诊","status":null,"standDeptId":"0","standDeptName":"","spId":null,"spCode":null,"verNum":null,"priority":null,"member":"DEPARTMENT_46293","score":0.0},{"hospitalId":"399","departmentId":"46292","departmentName":"肺科门诊","status":null,"standDeptId":"0","standDeptName":"","spId":null,"spCode":null,"verNum":null,"priority":null,"member":"DEPARTMENT_46292","score":0.0},{"hospitalId":"399","departmentId":"46291","departmentName":"介入科血管疾病微创门诊","status":null,"standDeptId":"0","standDeptName":"","spId":null,"spCode":null,"verNum":null,"priority":null,"member":"DEPARTMENT_46291","score":0.0},{"hospitalId":"399","departmentId":"46290","departmentName":"介入科肝胆胰肿瘤微创门诊","status":null,"standDeptId":"0","standDeptName":"","spId":null,"spCode":null,"verNum":null,"priority":null,"member":"DEPARTMENT_46290","score":0.0},{"hospitalId":"399","departmentId":"46289","departmentName":"介入科介入治疗门诊","status":null,"standDeptId":"0","standDeptName":"","spId":null,"spCode":null,"verNum":null,"priority":null,"member":"DEPARTMENT_46289","score":0.0},{"hospitalId":"399","departmentId":"46288","departmentName":"肿瘤科淋巴瘤门诊","status":null,"standDeptId":"0","standDeptName":"","spId":null,"spCode":null,"verNum":null,"priority":null,"member":"DEPARTMENT_46288","score":0.0},{"hospitalId":"399","departmentId":"46287","departmentName":"肿瘤内二科门诊","status":null,"standDeptId":"0","standDeptName":"","spId":null,"spCode":null,"verNum":null,"priority":null,"member":"DEPARTMENT_46287","score":0.0},{"hospitalId":"399","departmentId":"299594","departmentName":"东川神经外科垂体瘤门诊","status":null,"standDeptId":"0","standDeptName":"","spId":null,"spCode":null,"verNum":null,"priority":null,"member":"DEPARTMENT_299594","score":0.0},{"hospitalId":"399","departmentId":"298736","departmentName":"东川嗓音疾病门诊","status":null,"standDeptId":"0","standDeptName":"","spId":null,"spCode":null,"verNum":null,"priority":null,"member":"DEPARTMENT_298736","score":0.0},{"hospitalId":"399","departmentId":"297702","departmentName":"东川高危儿随诊门诊","status":null,"standDeptId":"0","standDeptName":"","spId":null,"spCode":null,"verNum":null,"priority":null,"member":"DEPARTMENT_297702","score":0.0},{"hospitalId":"399","departmentId":"26982","departmentName":"门诊部","status":null,"standDeptId":"0","standDeptName":"","spId":null,"spCode":null,"verNum":null,"priority":null,"member":"DEPARTMENT_26982","score":0.0},{"hospitalId":"399","departmentId":"26876","departmentName":"东老年病门诊","status":null,"standDeptId":"0","standDeptName":"","spId":null,"spCode":null,"verNum":null,"priority":null,"member":"DEPARTMENT_26876","score":0.0},{"hospitalId":"399","departmentId":"26837","departmentName":"风湿科关节炎门诊","status":null,"standDeptId":"0","standDeptName":"","spId":null,"spCode":null,"verNum":null,"priority":null,"member":"DEPARTMENT_26837","score":0.0},{"hospitalId":"399","departmentId":"260520","departmentName":"心抗凝精准用药咨询门诊","status":null,"standDeptId":"0","standDeptName":"","spId":null,"spCode":null,"verNum":null,"priority":null,"member":"DEPARTMENT_260520","score":0.0},{"hospitalId":"399","departmentId":"260069","departmentName":"东川泌尿系统肿瘤门诊","status":null,"standDeptId":"0","standDeptName":"","spId":null,"spCode":null,"verNum":null,"priority":null,"member":"DEPARTMENT_260069","score":0.0},{"hospitalId":"399","departmentId":"259077","departmentName":"东病区肝胆内科门诊","status":null,"standDeptId":"0","standDeptName":"","spId":null,"spCode":null,"verNum":null,"priority":null,"member":"DEPARTMENT_259077","score":0.0},{"hospitalId":"399","departmentId":"257234","departmentName":"东川精准用药咨询门诊","status":null,"standDeptId":"0","standDeptName":"","spId":null,"spCode":null,"verNum":null,"priority":null,"member":"DEPARTMENT_257234","score":0.0},{"hospitalId":"399","departmentId":"252782","departmentName":"东病区中医科2门诊","status":null,"standDeptId":"0","standDeptName":"","spId":null,"spCode":null,"verNum":null,"priority":null,"member":"DEPARTMENT_252782","score":0.0},{"hospitalId":"399","departmentId":"251589","departmentName":"东病区心身与睡眠门诊","status":null,"standDeptId":"0","standDeptName":"","spId":null,"spCode":null,"verNum":null,"priority":null,"member":"DEPARTMENT_251589","score":0.0},{"hospitalId":"399","departmentId":"251587","departmentName":"东川骨科脊柱外科门诊","status":null,"standDeptId":"0","standDeptName":"","spId":null,"spCode":null,"verNum":null,"priority":null,"member":"DEPARTMENT_251587","score":0.0},{"hospitalId":"399","departmentId":"214976","departmentName":"东川心血管慢性病门诊","status":null,"standDeptId":"0","standDeptName":"","spId":null,"spCode":null,"verNum":null,"priority":null,"member":"DEPARTMENT_214976","score":0.0},{"hospitalId":"399","departmentId":"204301","departmentName":"东川职工门诊","status":null,"standDeptId":"0","standDeptName":"","spId":null,"spCode":null,"verNum":null,"priority":null,"member":"DEPARTMENT_204301","score":0.0},{"hospitalId":"399","departmentId":"204290","departmentName":"心主动脉疾病门诊","status":null,"standDeptId":"0","standDeptName":"","spId":null,"spCode":null,"verNum":null,"priority":null,"member":"DEPARTMENT_204290","score":0.0},{"hospitalId":"399","departmentId":"193193","departmentName":"东川头颈肿瘤内科门诊","status":null,"standDeptId":"0","standDeptName":"","spId":null,"spCode":null,"verNum":null,"priority":null,"member":"DEPARTMENT_193193","score":0.0},{"hospitalId":"399","departmentId":"193190","departmentName":"东川内分泌甲状腺门诊","status":null,"standDeptId":"0","standDeptName":"","spId":null,"spCode":null,"verNum":null,"priority":null,"member":"DEPARTMENT_193190","score":0.0},{"hospitalId":"399","departmentId":"193187","departmentName":"东川痛风门诊","status":null,"standDeptId":"0","standDeptName":"","spId":null,"spCode":null,"verNum":null,"priority":null,"member":"DEPARTMENT_193187","score":0.0},{"hospitalId":"399","departmentId":"193184","departmentName":"东川骨科关节疾病门诊","status":null,"standDeptId":"0","standDeptName":"","spId":null,"spCode":null,"verNum":null,"priority":null,"member":"DEPARTMENT_193184","score":0.0},{"hospitalId":"399","departmentId":"183761","departmentName":"东川骨科疑难病会诊门诊","status":null,"standDeptId":"0","standDeptName":"","spId":null,"spCode":null,"verNum":null,"priority":null,"member":"DEPARTMENT_183761","score":0.0},{"hospitalId":"399","departmentId":"183759","departmentName":"东川头颈肿瘤专科门诊","status":null,"standDeptId":"0","standDeptName":"","spId":null,"spCode":null,"verNum":null,"priority":null,"member":"DEPARTMENT_183759","score":0.0}]}