{"resultCode":"0000","msg":"成功","response":[{"hospitalId":"1118","hospitalName":"广州中医药大学第一附属医院（机场路）","departmentId":"199388","departmentName":"妇科门诊","doctorId":"313180","doctorName":"曹蕾","status":null,"spId":null,"spCode":null,"regSubject":"","verNum":null,"priority":null,"sex":"0","birthday":"","title":"普通出诊4元","fee":"","intro":"","specialty":"暂无","notice":"","photo":"","hot":"1","level":"","sendSpCode":null,"reviewScore":"4","doctorsAttitude":"4","treatmentEffect":"4","favStatis":"","orderStatis":"","reviewStatis":"","hasResource":true,"schedules":[],"member":"DOCTOR_313180","score":0.0},{"hospitalId":"1118","hospitalName":"广州中医药大学第一附属医院（机场路）","departmentId":"199388","departmentName":"妇科门诊","doctorId":"313181","doctorName":"陈碧云","status":null,"spId":null,"spCode":null,"regSubject":"","verNum":null,"priority":null,"sex":"0","birthday":"","title":"副教授/副主任医师","fee":"","intro":"陈碧云;女;副主任医师;副教授;擅长妇科肿瘤、不孕症、尖锐湿疣等疾病的诊治。","specialty":"妇科肿瘤、不孕症、尖锐湿疣等疾病的诊治。","notice":"","photo":"http://183.63.133.156:8015/dl/photos/doctor/doctor_12402.jpg","hot":"1","level":"","sendSpCode":null,"reviewScore":"4","doctorsAttitude":"4","treatmentEffect":"4","favStatis":"","orderStatis":"","reviewStatis":"","hasResource":true,"schedules":[],"member":"DOCTOR_313181","score":0.0},{"hospitalId":"1118","hospitalName":"广州中医药大学第一附属医院（机场路）","departmentId":"199388","departmentName":"妇科门诊","doctorId":"313182","doctorName":"陈可敬","status":null,"spId":null,"spCode":null,"regSubject":"","verNum":null,"priority":null,"sex":"0","birthday":"","title":"副主任医师","fee":"","intro":"陈可敬;女;副主任医师;副教授;擅长诊治月经病、不孕不育、炎症、肿瘤等疾病。","specialty":"月经病、不孕不育、炎症、肿瘤","notice":"","photo":"http://183.63.133.156:8015/dl/photos/doctor/doctor_12397.jpg","hot":"1","level":"","sendSpCode":null,"reviewScore":"4","doctorsAttitude":"4","treatmentEffect":"4","favStatis":"","orderStatis":"","reviewStatis":"","hasResource":true,"schedules":[{"departmentCode":"44_0013000","departmentName":"妇科门诊","doctorCode":"44_01760","doctorName":"陈可敬","scheDate":"2016-07-18","amPm":"上午","state":"0","freeNum":"0","returnMsg":"1|1|1|1|1|1|1|1|1|1|1|1|1|1|1|1|1|1|1|1","payType":"0"},{"departmentCode":"44_0013000","departmentName":"妇科门诊","doctorCode":"44_01760","doctorName":"陈可敬","scheDate":"2016-07-20","amPm":"上午","state":"0","freeNum":"0","returnMsg":"1|1|1|1|1|1|1|1|1|1|1|1|1|1|1|1|1|1|1|1","payType":"0"},{"departmentCode":"44_0013000","departmentName":"妇科门诊","doctorCode":"44_01760","doctorName":"陈可敬","scheDate":"2016-07-21","amPm":"上午","state":"0","freeNum":"0","returnMsg":"1|1|1|1|1|1|1|1|1|1|1|1|1|1|1|1|1|1|1|1","payType":"0"},{"departmentCode":"44_0013000","departmentName":"妇科门诊","doctorCode":"44_01760","doctorName":"陈可敬","scheDate":"2016-07-23","amPm":"上午","state":"0","freeNum":"0","returnMsg":"1|1|1|1|1|1|1|1|1|1|1|1|1|1|1|1|1|1|1|1","payType":"0"}],"member":"DOCTOR_313182","score":0.0},{"hospitalId":"1118","hospitalName":"广州中医药大学第一附属医院（机场路）","departmentId":"199388","departmentName":"妇科门诊","doctorId":"313183","doctorName":"邓高丕","status":null,"spId":null,"spCode":null,"regSubject":"3","verNum":null,"priority":null,"sex":"1","birthday":"","title":"教授","fee":"","intro":"邓高丕男;广州中医药大学教授、主任中医师、中西医结合临床（妇科）博士研究生导师。1985年毕业于广州中医药大学医疗专业;1988年读研究生课程一年;1991年在广东省人民医院进修妇产科临床一年。2003年8月～12月在香港中文大学任访问学人。现任广州中医药大学第一临床医学院妇科教研室副主任、第一附属医院一妇科主任；兼任国家中医药管理局重点专科（中医妇科）项目负责人和学术带头人、中国中西医结合学会妇产科专业委员会委员、广东省中医西医结合学会妇产科专业委员会副主任委员、广东优生优育协会专家委员会委员、新世纪全国高等中医药院校七年制规划教材《中医妇科学》和中西医结合临床医学专业规划教材《中西医结合妇科学》编委、《中国实用妇科与产科杂志》编委、《新中医》杂志编委、《中国医科大学学报》学术审稿专家、国家基本医疗保险评审专家、全军卫生技术资格考试命题委员会委员、广东省政府采购评审专家、广东省药品注册审评专家、广东省药物临床试验机构资格认定专家、广东省医学会和广州市医学会医疗事故技术鉴定专家。","specialty":"治妇科肿瘤、异位妊娠、盆腔炎、子宫内膜异位症、功血等妇科痛证、血证。","notice":"","photo":"http://183.63.133.156:8015/dl/photos/doctor/doctor_12385.jpg","hot":"1","level":"","sendSpCode":null,"reviewScore":"4","doctorsAttitude":"4","treatmentEffect":"4","favStatis":"","orderStatis":"","reviewStatis":"","hasResource":true,"schedules":[],"member":"DOCTOR_313183","score":0.0},{"hospitalId":"1118","hospitalName":"广州中医药大学第一附属医院（机场路）","departmentId":"199388","departmentName":"妇科门诊","doctorId":"313184","doctorName":"范扬卿","status":null,"spId":null,"spCode":null,"regSubject":"","verNum":null,"priority":null,"sex":"0","birthday":"","title":"副主任医师","fee":"","intro":"范杨卿;女;副主任医师;1975年毕业于广州中医药大学本科毕业后留校工作;一直从事中医妇科学的教学、科研;临床医疗工作;临床和教学经验丰富;并有较强的科研能力;是“麒麟丸”治疗不孕不育症研究课题的主要成员；该课题获广东省医药科技进步一等奖;省科技进步三等奖；担任各个不同班种中医妇科学课程主讲教师;教学评估成绩优良;主编《孕期保健》、《中医妇科学临床见习指导》等教材;参加编写《中医急诊学》等教材;并获校级成果奖；发表《补肾助育汤治疗男性不育症》、《辨证治疗盆腔炎》等多篇学术论文;在中西医结合防治妇科经、带、胎、产等疾病方面有较深造诣;尤其擅长于治疗不孕不育症、月经病、妇科肿瘤、盆腔类症等疾病。","specialty":"治疗不孕不育症、月经病、妇科肿瘤、盆腔类症等疾病。","notice":"","photo":"http://183.63.133.156:8015/dl/photos/doctor/doctor_12394.jpg","hot":"1","level":"","sendSpCode":null,"reviewScore":"4","doctorsAttitude":"4","treatmentEffect":"4","favStatis":"","orderStatis":"","reviewStatis":"","hasResource":true,"schedules":[{"departmentCode":"44_0013000","departmentName":"妇科门诊","doctorCode":"44_73260","doctorName":"范扬卿","scheDate":"2016-07-18","amPm":"上午","state":"0","freeNum":"0","returnMsg":"1|1|1|1|1|1|1|1|1|1|1|1|1|1|1|1|1|1|1|1|1|1|1|1|1|1|1|1|1|1|1","payType":"0"},{"departmentCode":"44_0013000","departmentName":"妇科门诊","doctorCode":"44_73260","doctorName":"范扬卿","scheDate":"2016-07-19","amPm":"上午","state":"0","freeNum":"0","returnMsg":"1|1|1|1|1|1|1|1|1|1|1|1|1|1|1|1|1|1|1|1|1|1|1|1|1|1|1|1|1|1|1","payType":"0"},{"departmentCode":"44_0013000","departmentName":"妇科门诊","doctorCode":"44_73260","doctorName":"范扬卿","scheDate":"2016-07-20","amPm":"上午","state":"0","freeNum":"0","returnMsg":"1|1|1|1|1|1|1|1|1|1|1|1|1|1|1|1|1|1|1|1|1|1|1|1|1|1|1|1|1|1|1","payType":"0"},{"departmentCode":"44_0013000","departmentName":"妇科门诊","doctorCode":"44_73260","doctorName":"范扬卿","scheDate":"2016-07-21","amPm":"上午","state":"0","freeNum":"0","returnMsg":"1|1|1|1|1|1|1|1|1|1|1|1|1|1|1|1|1|1|1|1|1|1|1|1|1|1|1|1|1|1|1","payType":"0"},{"departmentCode":"44_0013000","departmentName":"妇科门诊","doctorCode":"44_73260","doctorName":"范扬卿","scheDate":"2016-07-22","amPm":"上午","state":"0","freeNum":"0","returnMsg":"1|1|1|1|1|1|1|1|1|1|1|1|1|1|1|1|1|1|1|1|1|1|1|1|1|1|1|1|1|1|1","payType":"0"}],"member":"DOCTOR_313184","score":0.0},{"hospitalId":"1118","hospitalName":"广州中医药大学第一附属医院（机场路）","departmentId":"199388","departmentName":"妇科门诊","doctorId":"313185","doctorName":"冯金英","status":null,"spId":null,"spCode":null,"regSubject":"","verNum":null,"priority":null,"sex":"0","birthday":"","title":"副教授","fee":"","intro":"冯金英;女;副教授;早年毕业于广州中医学院。从事妇科临床工作近三十年。擅长治疗妇科炎症、月经痛、异常出血、不孕症等。","specialty":"月经病、不孕不育、炎症","notice":"","photo":"http://183.63.133.156:8015/dl/photos/doctor/doctor_12403.jpg","hot":"1","level":"","sendSpCode":null,"reviewScore":"4","doctorsAttitude":"4","treatmentEffect":"4","favStatis":"","orderStatis":"","reviewStatis":"","hasResource":true,"schedules":[{"departmentCode":"44_0013000","departmentName":"妇科门诊","doctorCode":"44_05120","doctorName":"冯金英","scheDate":"2016-07-18","amPm":"上午","state":"0","freeNum":"0","returnMsg":"1|1|1|1|1|1|1|1|1|1|1|1|1|1|1|1|1|1|1|1|1|1|1|1|1|1|1|1|1|1|1|1|1|1|1|1|1|1|1","payType":"0"},{"departmentCode":"44_0013000","departmentName":"妇科门诊","doctorCode":"44_05120","doctorName":"冯金英","scheDate":"2016-07-20","amPm":"上午","state":"0","freeNum":"0","returnMsg":"1|1|1|1|1|1|1|1|1|1|1|1|1|1|1|1|1|1|1|1|1|1|1|1|1|1|1|1|1|1|1|1|1|1|1|1|1|1|1","payType":"0"},{"departmentCode":"44_0013000","departmentName":"妇科门诊","doctorCode":"44_05120","doctorName":"冯金英","scheDate":"2016-07-21","amPm":"上午","state":"0","freeNum":"0","returnMsg":"1|1|1|1|1|1|1|1|1|1|1|1|1|1|1|1|1|1|1|1|1|1|1|1|1|1|1|1|1|1|1|1|1|1|1|1|1|1|1","payType":"0"},{"departmentCode":"44_0013000","departmentName":"妇科门诊","doctorCode":"44_05120","doctorName":"冯金英","scheDate":"2016-07-22","amPm":"上午","state":"0","freeNum":"0","returnMsg":"1|1|1|1|1|1|1|1|1|1|1|1|1|1|1|1|1|1|1|1|1|1|1|1|1|1|1|1|1|1|1|1|1|1|1|1|1|1|1","payType":"0"},{"departmentCode":"44_0013000","departmentName":"妇科门诊","doctorCode":"44_05120","doctorName":"冯金英","scheDate":"2016-07-23","amPm":"上午","state":"0","freeNum":"0","returnMsg":"1|1|1|1|1|1|1|1|1|1|1|1|1|1|1|1|1|1|1|1|1|1|1|1|1|1|1|1|1|1|1|1|1|1|1|1|1|1|1","payType":"0"}],"member":"DOCTOR_313185","score":0.0},{"hospitalId":"1118","hospitalName":"广州中医药大学第一附属医院（机场路）","departmentId":"199388","departmentName":"妇科门诊","doctorId":"313186","doctorName":"冯倩怡","status":null,"spId":null,"spCode":null,"regSubject":"","verNum":null,"priority":null,"sex":"-1","birthday":"","title":"主治医师","fee":"","intro":"冯倩怡;女;主治医师","specialty":"","notice":"","photo":"http://183.63.133.156:8015/dl/photos/doctor/doctor_12383.jpg","hot":"1","level":"","sendSpCode":null,"reviewScore":"4","doctorsAttitude":"4","treatmentEffect":"4","favStatis":"","orderStatis":"","reviewStatis":"","hasResource":true,"schedules":[{"departmentCode":"44_0013000","departmentName":"妇科门诊","doctorCode":"44_03625","doctorName":"冯倩怡","scheDate":"2016-07-19","amPm":"下午","state":"0","freeNum":"0","returnMsg":"1|1|1|1|1|1|1|1|1|1","payType":"0"}],"member":"DOCTOR_313186","score":0.0},{"hospitalId":"1118","hospitalName":"广州中医药大学第一附属医院（机场路）","departmentId":"199388","departmentName":"妇科门诊","doctorId":"313187","doctorName":"高克非","status":null,"spId":null,"spCode":null,"regSubject":"","verNum":null,"priority":null,"sex":"-1","birthday":"","title":"普通出诊4元","fee":"","intro":"","specialty":"","notice":"","photo":"","hot":"1","level":"","sendSpCode":null,"reviewScore":"4","doctorsAttitude":"4","treatmentEffect":"4","favStatis":"","orderStatis":"","reviewStatis":"","hasResource":true,"schedules":[],"member":"DOCTOR_313187","score":0.0}],"sum":45,"days":["2016-07-16 星期六","2016-07-17 星期日","2016-07-18 星期一","2016-07-19 星期二","2016-07-20 星期三","2016-07-21 星期四","2016-07-22 星期五","2016-07-23 星期六","2016-07-24 星期日","2016-07-25 星期一","2016-07-26 星期二","2016-07-27 星期三","2016-07-28 星期四","2016-07-29 星期五","2016-07-30 星期六","2016-07-31 星期日","2016-08-01 星期一","2016-08-02 星期二","2016-08-03 星期三","2016-08-04 星期四","2016-08-05 星期五","2016-08-06 星期六","2016-08-07 星期日","2016-08-08 星期一","2016-08-09 星期二","2016-08-10 星期三","2016-08-11 星期四","2016-08-12 星期五","2016-08-13 星期六","2016-08-14 星期日","2016-08-15 星期一","2016-08-16 星期二","2016-08-17 星期三"],"index":8}