{"resultCode":"0000","msg":"成功","response":[{"hospitalId":"321","hospitalName":"广州市番禺中心医院","departmentId":"45308","departmentName":"中医风湿痛症专家","doctorId":"163493","doctorName":"申朝霞","status":null,"spId":null,"spCode":null,"regSubject":"","verNum":null,"priority":null,"sex":"0","birthday":"","title":"副主任中医师","fee":"","intro":"暂无","specialty":"广州中医药大学本科毕业，从事中医临床工作20多年，擅长治疗内科杂病，尤其对呼吸、消化、风湿性疾病、颈椎病以及皮肤和妇儿科疾病。","notice":"","photo":"http://183.63.133.156:8015/dl/photos/doctor/doctor_163493.jpg","hot":"1","level":"","sendSpCode":null,"reviewScore":"4","doctorsAttitude":"4","treatmentEffect":"4","favStatis":"","orderStatis":"","reviewStatis":"","hasResource":true,"schedules":[{"departmentCode":"","departmentName":"","doctorCode":"15_0753","doctorName":"","scheDate":"2016-07-21","amPm":"上午","state":"0","freeNum":"42","returnMsg":"1","payType":"0"},{"departmentCode":"","departmentName":"","doctorCode":"15_0753","doctorName":"","scheDate":"2016-07-21","amPm":"下午","state":"0","freeNum":"25","returnMsg":"1","payType":"0"}],"member":"DOCTOR_163493","score":0.0}],"sum":1,"days":["2016-07-17 星期日","2016-07-18 星期一","2016-07-19 星期二","2016-07-20 星期三","2016-07-21 星期四","2016-07-22 星期五","2016-07-23 星期六","2016-07-24 星期日"],"index":1}